Workbook
Name CalendarYear: January!$AH$6
Name ColumnTitle13: EmployeeName[[#Headers],[Employee Names]]
Name Employee_Absence_Title: January!$B$1
Name Key_name: January!$B$4
Name KeyCustom1: January!$N$4
Name KeyCustom1Label: January!$O$4
Name KeyCustom2: January!$R$4
Name KeyCustom2Label: January!$S$4
Name KeyPersonal: January!$G$4
Name KeyPersonalLabel: January!$H$4
Name KeySick: January!$K$4
Name KeySickLabel: January!$L$4
Name KeyVacation: January!$C$4
Name KeyVacationLabel: January!$D$4
Name MonthName: April!$B$7
Name MonthName: August!$B$2
Name MonthName: December!$B$2
Name MonthName: February!$B$2
Name MonthName: Jan!$C$2
Name MonthName: January!$B$2
Name MonthName: July!$B$2
Name MonthName: June!$B$2
Name MonthName: March!$B$2
Name MonthName: May!$B$4
Name MonthName: November!$C$2
Name MonthName: October!$C$2
Name MonthName: September!$B$2
Name Title1: January[[#Headers],[Employee name]]
Name Title10: October[[#Headers],[Employee name]]
Name Title11: November[[#Headers],[Employee name]]
Name Title12: December[[#Headers],[Employee name]]
Name Title2: February[[#Headers],[Employee name]]
Name Title3: March[[#Headers],[Employee name]]
Name Title4: #REF!
Name Title5: #REF!
Name Title6: June[[#Headers],[Employee name]]
Name Title7: July[[#Headers],[Employee name]]
Name Title8: August[[#Headers],[Employee name]]
Name Title9: September[[#Headers],[Employee name]]

Sheet January
B1: Employee absence schedule
B2: January
B4: Absence type key | C4: V | D4: Vacation | G4: P | H4: Personal | K4: S | L4: Sick | O4: Custom 1 | S4: Custom 2
C6: Dates of absence | AH6: =YEAR(TODAY()) -> 2026
C7: =TEXT(WEEKDAY(DATE(CalendarYear,1,1),1),"aaa") -> Thu | D7: =TEXT(WEEKDAY(DATE(CalendarYear,1,2),1),"aaa") -> Fri | E7: =TEXT(WEEKDAY(DATE(CalendarYear,1,3),1),"aaa") -> Sat | F7: =TEXT(WEEKDAY(DATE(CalendarYear,1,4),1),"aaa") -> Sun | G7: =TEXT(WEEKDAY(DATE(CalendarYear,1,5),1),"aaa") -> Mon | H7: =TEXT(WEEKDAY(DATE(CalendarYear,1,6),1),"aaa") -> Tue | I7: =TEXT(WEEKDAY(DATE(CalendarYear,1,7),1),"aaa") -> Wed | J7: =TEXT(WEEKDAY(DATE(CalendarYear,1,8),1),"aaa") -> Thu | K7: =TEXT(WEEKDAY(DATE(CalendarYear,1,9),1),"aaa") -> Fri | L7: =TEXT(WEEKDAY(DATE(CalendarYear,1,10),1),"aaa") -> Sat | M7: =TEXT(WEEKDAY(DATE(CalendarYear,1,11),1),"aaa") -> Sun | N7: =TEXT(WEEKDAY(DATE(CalendarYear,1,12),1),"aaa") -> Mon | O7: =TEXT(WEEKDAY(DATE(CalendarYear,1,13),1),"aaa") -> Tue | P7: =TEXT(WEEKDAY(DATE(CalendarYear,1,14),1),"aaa") -> Wed | Q7: =TEXT(WEEKDAY(DATE(CalendarYear,1,15),1),"aaa") -> Thu | R7: =TEXT(WEEKDAY(DATE(CalendarYear,1,16),1),"aaa") -> Fri | S7: =TEXT(WEEKDAY(DATE(CalendarYear,1,17),1),"aaa") -> Sat | T7: =TEXT(WEEKDAY(DATE(CalendarYear,1,18),1),"aaa") -> Sun | U7: =TEXT(WEEKDAY(DATE(CalendarYear,1,19),1),"aaa") -> Mon | V7: =TEXT(WEEKDAY(DATE(CalendarYear,1,20),1),"aaa") -> Tue | W7: =TEXT(WEEKDAY(DATE(CalendarYear,1,21),1),"aaa") -> Wed | X7: =TEXT(WEEKDAY(DATE(CalendarYear,1,22),1),"aaa") -> Thu | Y7: =TEXT(WEEKDAY(DATE(CalendarYear,1,23),1),"aaa") -> Fri | Z7: =TEXT(WEEKDAY(DATE(CalendarYear,1,24),1),"aaa") -> Sat | AA7: =TEXT(WEEKDAY(DATE(CalendarYear,1,25),1),"aaa") -> Sun | AB7: =TEXT(WEEKDAY(DATE(CalendarYear,1,26),1),"aaa") -> Mon | AC7: =TEXT(WEEKDAY(DATE(CalendarYear,1,27),1),"aaa") -> Tue | AD7: =TEXT(WEEKDAY(DATE(CalendarYear,1,28),1),"aaa") -> Wed | AE7: =TEXT(WEEKDAY(DATE(CalendarYear,1,29),1),"aaa") -> Thu | AF7: =TEXT(WEEKDAY(DATE(CalendarYear,1,30),1),"aaa") -> Fri | AG7: =TEXT(WEEKDAY(DATE(CalendarYear,1,31),1),"aaa") -> Sat
B8: Employee name | C8: 1 | D8: 2 | E8: 3 | F8: 4 | G8: 5 | H8: 6 | I8: 7 | J8: 8 | K8: 9 | L8: 10 | M8: 11 | N8: 12 | O8: 13 | P8: 14 | Q8: 15 | R8: 16 | S8: 17 | T8: 18 | U8: 19 | V8: 20 | W8: 21 | X8: 22 | Y8: 23 | Z8: 24 | AA8: 25 | AB8: 26 | AC8: 27 | AD8: 28 | AE8: 29 | AF8: 30 | AG8: 31 | AH8: Total days
B9: Harsimran Brar | E9: V | F9: V | G9: V | H9: V | O9: V | AH9: =COUNTA(January!$C9:$AG9) -> 5
B10: Jordan Mitchell | G10: S | H10: S | M10: P | V10: S | AA10: V | AB10: V | AC10: V | AH10: =COUNTA(January!$C10:$AG10) -> 7
B11: Asaf Karten | E11: P | P11: S | AE11: S | AH11: =COUNTA(January!$C11:$AG11) -> 3
B12: Vanja Jovanovic | I12: P | U12: V | V12: V | W12: V | AH12: =COUNTA(January!$C12:$AG12) -> 4
B13: Madison Butler | F13: S | G13: V | H13: V | S13: S | Z13: S | AG13: V | AH13: =COUNTA(January!$C13:$AG13) -> 6
B14: =MonthName&" total" -> January total | C14: =SUBTOTAL(103,January!$C$9:$C$13) -> 0 | D14: =SUBTOTAL(103,January!$D$9:$D$13) -> 0 | E14: =SUBTOTAL(103,January!$E$9:$E$13) -> 2 | F14: =SUBTOTAL(103,January!$F$9:$F$13) -> 2 | G14: =SUBTOTAL(103,January!$G$9:$G$13) -> 3 | H14: =SUBTOTAL(103,January!$H$9:$H$13) -> 3 | I14: =SUBTOTAL(103,January!$I$9:$I$13) -> 1 | J14: =SUBTOTAL(103,January!$J$9:$J$13) -> 0 | K14: =SUBTOTAL(103,January!$K$9:$K$13) -> 0 | L14: =SUBTOTAL(103,January!$L$9:$L$13) -> 0 | M14: =SUBTOTAL(103,January!$M$9:$M$13) -> 1 | N14: =SUBTOTAL(103,January!$N$9:$N$13) -> 0 | O14: =SUBTOTAL(103,January!$O$9:$O$13) -> 1 | P14: =SUBTOTAL(103,January!$P$9:$P$13) -> 1 | Q14: =SUBTOTAL(103,January!$Q$9:$Q$13) -> 0 | R14: =SUBTOTAL(103,January!$R$9:$R$13) -> 0 | S14: =SUBTOTAL(103,January!$S$9:$S$13) -> 1 | T14: =SUBTOTAL(103,January!$T$9:$T$13) -> 0 | U14: =SUBTOTAL(103,January!$U$9:$U$13) -> 1 | V14: =SUBTOTAL(103,January!$V$9:$V$13) -> 2 | W14: =SUBTOTAL(103,January!$W$9:$W$13) -> 1 | X14: =SUBTOTAL(103,January!$X$9:$X$13) -> 0 | Y14: =SUBTOTAL(103,January!$Y$9:$Y$13) -> 0 | Z14: =SUBTOTAL(103,January!$Z$9:$Z$13) -> 1 | AA14: =SUBTOTAL(103,January!$AA$9:$AA$13) -> 1 | AB14: =SUBTOTAL(103,January!$AB$9:$AB$13) -> 1 | AC14: =SUBTOTAL(103,January!$AC$9:$AC$13) -> 1 | AD14: =SUBTOTAL(103,January!$AD$9:$AD$13) -> 0 | AE14: =SUBTOTAL(103,January!$AE$9:$AE$13) -> 1 | AF14: =SUBTOTAL(103,January!$AF$9:$AF$13) -> 0 | AG14: =SUBTOTAL(103,January!$AG$9:$AG$13) -> 1 | AH14: =SUBTOTAL(109,January[Total days]) -> 25

Sheet February
B1: Employee absence schedule
B2: February
B4: Absence type key | C4: V | D4: Vacation | G4: P | H4: Personal | K4: S | L4: Sick | O4: Custom 1 | S4: Custom 2
C6: Dates of absence | AH6: =CalendarYear -> 2026
C7: =TEXT(WEEKDAY(DATE(CalendarYear,2,1),1),"aaa") -> Sun | D7: =TEXT(WEEKDAY(DATE(CalendarYear,2,2),1),"aaa") -> Mon | E7: =TEXT(WEEKDAY(DATE(CalendarYear,2,3),1),"aaa") -> Tue | F7: =TEXT(WEEKDAY(DATE(CalendarYear,2,4),1),"aaa") -> Wed | G7: =TEXT(WEEKDAY(DATE(CalendarYear,2,5),1),"aaa") -> Thu | H7: =TEXT(WEEKDAY(DATE(CalendarYear,2,6),1),"aaa") -> Fri | I7: =TEXT(WEEKDAY(DATE(CalendarYear,2,7),1),"aaa") -> Sat | J7: =TEXT(WEEKDAY(DATE(CalendarYear,2,8),1),"aaa") -> Sun | K7: =TEXT(WEEKDAY(DATE(CalendarYear,2,9),1),"aaa") -> Mon | L7: =TEXT(WEEKDAY(DATE(CalendarYear,2,10),1),"aaa") -> Tue | M7: =TEXT(WEEKDAY(DATE(CalendarYear,2,11),1),"aaa") -> Wed | N7: =TEXT(WEEKDAY(DATE(CalendarYear,2,12),1),"aaa") -> Thu | O7: =TEXT(WEEKDAY(DATE(CalendarYear,2,13),1),"aaa") -> Fri | P7: =TEXT(WEEKDAY(DATE(CalendarYear,2,14),1),"aaa") -> Sat | Q7: =TEXT(WEEKDAY(DATE(CalendarYear,2,15),1),"aaa") -> Sun | R7: =TEXT(WEEKDAY(DATE(CalendarYear,2,16),1),"aaa") -> Mon | S7: =TEXT(WEEKDAY(DATE(CalendarYear,2,17),1),"aaa") -> Tue | T7: =TEXT(WEEKDAY(DATE(CalendarYear,2,18),1),"aaa") -> Wed | U7: =TEXT(WEEKDAY(DATE(CalendarYear,2,19),1),"aaa") -> Thu | V7: =TEXT(WEEKDAY(DATE(CalendarYear,2,20),1),"aaa") -> Fri | W7: =TEXT(WEEKDAY(DATE(CalendarYear,2,21),1),"aaa") -> Sat | X7: =TEXT(WEEKDAY(DATE(CalendarYear,2,22),1),"aaa") -> Sun | Y7: =TEXT(WEEKDAY(DATE(CalendarYear,2,23),1),"aaa") -> Mon | Z7: =TEXT(WEEKDAY(DATE(CalendarYear,2,24),1),"aaa") -> Tue | AA7: =TEXT(WEEKDAY(DATE(CalendarYear,2,25),1),"aaa") -> Wed | AB7: =TEXT(WEEKDAY(DATE(CalendarYear,2,26),1),"aaa") -> Thu | AC7: =TEXT(WEEKDAY(DATE(CalendarYear,2,27),1),"aaa") -> Fri | AD7: =TEXT(WEEKDAY(DATE(CalendarYear,2,28),1),"aaa") -> Sat | AE7: =TEXT(WEEKDAY(DATE(CalendarYear,2,29),1),"aaa") -> Sun
B8: Employee name | C8: 1 | D8: 2 | E8: 3 | F8: 4 | G8: 5 | H8: 6 | I8: 7 | J8: 8 | K8: 9 | L8: 10 | M8: 11 | N8: 12 | O8: 13 | P8: 14 | Q8: 15 | R8: 16 | S8: 17 | T8: 18 | U8: 19 | V8: 20 | W8: 21 | X8: 22 | Y8: 23 | Z8: 24 | AA8: 25 | AB8: 26 | AC8: 27 | AD8: 28 | AE8: 29 | AH8: Total days
B9: Harsimran Brar | E9: V | F9: V | G9: V | H9: V | O9: V | AH9: =COUNTA(February[[#This Row],[1]:[29]]) -> 5
B10: Jordan Mitchell | G10: S | H10: S | M10: P | V10: S | AA10: V | AB10: V | AC10: V | AH10: =COUNTA(February[[#This Row],[1]:[29]]) -> 7
B11: Asaf Karten | AH11: =COUNTA(February[[#This Row],[1]:[29]]) -> 0
B12: Vanja Jovanovic | E12: S | P12: S | T12: P | AD12: S | AH12: =COUNTA(February[[#This Row],[1]:[29]]) -> 4
B13: Madison Butler | J13: V | K13: V | L13: V | M13: V | Z13: S | AH13: =COUNTA(February[[#This Row],[1]:[29]]) -> 5
B14: =MonthName&" total" -> February total | C14: =SUBTOTAL(103,February[1]) -> 0 | D14: =SUBTOTAL(103,February[2]) -> 0 | E14: =SUBTOTAL(103,February[3]) -> 2 | F14: =SUBTOTAL(103,February[4]) -> 1 | G14: =SUBTOTAL(103,February[5]) -> 2 | H14: =SUBTOTAL(103,February[6]) -> 2 | I14: =SUBTOTAL(103,February[7]) -> 0 | J14: =SUBTOTAL(103,February[8]) -> 1 | K14: =SUBTOTAL(103,February[9]) -> 1 | L14: =SUBTOTAL(103,February[10]) -> 1 | M14: =SUBTOTAL(103,February[11]) -> 2 | N14: =SUBTOTAL(103,February[12]) -> 0 | O14: =SUBTOTAL(103,February[13]) -> 1 | P14: =SUBTOTAL(103,February[14]) -> 1 | Q14: =SUBTOTAL(103,February[15]) -> 0 | R14: =SUBTOTAL(103,February[16]) -> 0 | S14: =SUBTOTAL(103,February[17]) -> 0 | T14: =SUBTOTAL(103,February[18]) -> 1 | U14: =SUBTOTAL(103,February[19]) -> 0 | V14: =SUBTOTAL(103,February[20]) -> 1 | W14: =SUBTOTAL(103,February[21]) -> 0 | X14: =SUBTOTAL(103,February[22]) -> 0 | Y14: =SUBTOTAL(103,February[23]) -> 0 | Z14: =SUBTOTAL(103,February[24]) -> 1 | AA14: =SUBTOTAL(103,February[25]) -> 1 | AB14: =SUBTOTAL(103,February[26]) -> 1 | AC14: =SUBTOTAL(103,February[27]) -> 1 | AD14: =SUBTOTAL(103,February[28]) -> 1 | AE14: =SUBTOTAL(103,February[29]) -> 0 | AH14: =SUBTOTAL(109,February[Total days]) -> 21

Sheet March
B1: Employee absence schedule
B2: March
B4: Absence type key | C4: V | D4: Vacation | G4: P | H4: Personal | K4: S | L4: Sick | O4: Custom 1 | S4: Custom 2
C6: Dates of absence | AH6: =CalendarYear -> 2026
C7: =TEXT(WEEKDAY(DATE(CalendarYear,3,1),1),"aaa") -> Sun | D7: =TEXT(WEEKDAY(DATE(CalendarYear,3,2),1),"aaa") -> Mon | E7: =TEXT(WEEKDAY(DATE(CalendarYear,3,3),1),"aaa") -> Tue | F7: =TEXT(WEEKDAY(DATE(CalendarYear,3,4),1),"aaa") -> Wed | G7: =TEXT(WEEKDAY(DATE(CalendarYear,3,5),1),"aaa") -> Thu | H7: =TEXT(WEEKDAY(DATE(CalendarYear,3,6),1),"aaa") -> Fri | I7: =TEXT(WEEKDAY(DATE(CalendarYear,3,7),1),"aaa") -> Sat | J7: =TEXT(WEEKDAY(DATE(CalendarYear,3,8),1),"aaa") -> Sun | K7: =TEXT(WEEKDAY(DATE(CalendarYear,3,9),1),"aaa") -> Mon | L7: =TEXT(WEEKDAY(DATE(CalendarYear,3,10),1),"aaa") -> Tue | M7: =TEXT(WEEKDAY(DATE(CalendarYear,3,11),1),"aaa") -> Wed | N7: =TEXT(WEEKDAY(DATE(CalendarYear,3,12),1),"aaa") -> Thu | O7: =TEXT(WEEKDAY(DATE(CalendarYear,3,13),1),"aaa") -> Fri | P7: =TEXT(WEEKDAY(DATE(CalendarYear,3,14),1),"aaa") -> Sat | Q7: =TEXT(WEEKDAY(DATE(CalendarYear,3,15),1),"aaa") -> Sun | R7: =TEXT(WEEKDAY(DATE(CalendarYear,3,16),1),"aaa") -> Mon | S7: =TEXT(WEEKDAY(DATE(CalendarYear,3,17),1),"aaa") -> Tue | T7: =TEXT(WEEKDAY(DATE(CalendarYear,3,18),1),"aaa") -> Wed | U7: =TEXT(WEEKDAY(DATE(CalendarYear,3,19),1),"aaa") -> Thu | V7: =TEXT(WEEKDAY(DATE(CalendarYear,3,20),1),"aaa") -> Fri | W7: =TEXT(WEEKDAY(DATE(CalendarYear,3,21),1),"aaa") -> Sat | X7: =TEXT(WEEKDAY(DATE(CalendarYear,3,22),1),"aaa") -> Sun | Y7: =TEXT(WEEKDAY(DATE(CalendarYear,3,23),1),"aaa") -> Mon | Z7: =TEXT(WEEKDAY(DATE(CalendarYear,3,24),1),"aaa") -> Tue | AA7: =TEXT(WEEKDAY(DATE(CalendarYear,3,25),1),"aaa") -> Wed | AB7: =TEXT(WEEKDAY(DATE(CalendarYear,3,26),1),"aaa") -> Thu | AC7: =TEXT(WEEKDAY(DATE(CalendarYear,3,27),1),"aaa") -> Fri | AD7: =TEXT(WEEKDAY(DATE(CalendarYear,3,28),1),"aaa") -> Sat | AE7: =TEXT(WEEKDAY(DATE(CalendarYear,3,29),1),"aaa") -> Sun | AF7: =TEXT(WEEKDAY(DATE(CalendarYear,3,30),1),"aaa") -> Mon | AG7: =TEXT(WEEKDAY(DATE(CalendarYear,3,31),1),"aaa") -> Tue
B8: Employee name | C8: 1 | D8: 2 | E8: 3 | F8: 4 | G8: 5 | H8: 6 | I8: 7 | J8: 8 | K8: 9 | L8: 10 | M8: 11 | N8: 12 | O8: 13 | P8: 14 | Q8: 15 | R8: 16 | S8: 17 | T8: 18 | U8: 19 | V8: 20 | W8: 21 | X8: 22 | Y8: 23 | Z8: 24 | AA8: 25 | AB8: 26 | AC8: 27 | AD8: 28 | AE8: 29 | AF8: 30 | AG8: 31 | AH8: Total days
B9: Harsimran Brar | AH9: =COUNTA(March[[#This Row],[1]:[31]]) -> 0
B10: Jordan Mitchell | AH10: =COUNTA(March[[#This Row],[1]:[31]]) -> 0
B11: Asaf Karten | AH11: =COUNTA(March[[#This Row],[1]:[31]]) -> 0
B12: Vanja Jovanovic | AH12: =COUNTA(March[[#This Row],[1]:[31]]) -> 0
B13: Madison Butler | AH13: =COUNTA(March[[#This Row],[1]:[31]]) -> 0
B14: =MonthName&" Total" -> March Total | C14: =SUBTOTAL(103,March[1]) -> 0 | D14: =SUBTOTAL(103,March[2]) -> 0 | E14: =SUBTOTAL(103,March[3]) -> 0 | F14: =SUBTOTAL(103,March[4]) -> 0 | G14: =SUBTOTAL(103,March[5]) -> 0 | H14: =SUBTOTAL(103,March[6]) -> 0 | I14: =SUBTOTAL(103,March[7]) -> 0 | J14: =SUBTOTAL(103,March[8]) -> 0 | K14: =SUBTOTAL(103,March[9]) -> 0 | L14: =SUBTOTAL(103,March[10]) -> 0 | M14: =SUBTOTAL(103,March[11]) -> 0 | N14: =SUBTOTAL(103,March[12]) -> 0 | O14: =SUBTOTAL(103,March[13]) -> 0 | P14: =SUBTOTAL(103,March[14]) -> 0 | Q14: =SUBTOTAL(103,March[15]) -> 0 | R14: =SUBTOTAL(103,March[16]) -> 0 | S14: =SUBTOTAL(103,March[17]) -> 0 | T14: =SUBTOTAL(103,March[18]) -> 0 | U14: =SUBTOTAL(103,March[19]) -> 0 | V14: =SUBTOTAL(103,March[20]) -> 0 | W14: =SUBTOTAL(103,March[21]) -> 0 | X14: =SUBTOTAL(103,March[22]) -> 0 | Y14: =SUBTOTAL(103,March[23]) -> 0 | Z14: =SUBTOTAL(103,March[24]) -> 0 | AA14: =SUBTOTAL(103,March[25]) -> 0 | AB14: =SUBTOTAL(103,March[26]) -> 0 | AC14: =SUBTOTAL(103,March[27]) -> 0 | AD14: =SUBTOTAL(103,March[28]) -> 0 | AE14: =SUBTOTAL(103,March[29]) -> 0 | AF14: =SUBTOTAL(109,March[30]) -> 0 | AG14: =SUBTOTAL(109,March[31]) -> 0 | AH14: =SUBTOTAL(109,March[Total days]) -> 0

Sheet April
B1: Employee absence schedule
B2: April
AH4: Meal/day
AH5: 20000
C6: Dates of absence | AH6: =CalendarYear -> 2026
C7: =TEXT(WEEKDAY(DATE(CalendarYear,4,1),1),"aaa") -> Wed | D7: =TEXT(WEEKDAY(DATE(CalendarYear,4,2),1),"aaa") -> Thu | E7: =TEXT(WEEKDAY(DATE(CalendarYear,4,3),1),"aaa") -> Fri | F7: =TEXT(WEEKDAY(DATE(CalendarYear,4,4),1),"aaa") -> Sat | G7: =TEXT(WEEKDAY(DATE(CalendarYear,4,5),1),"aaa") -> Sun | H7: =TEXT(WEEKDAY(DATE(CalendarYear,4,6),1),"aaa") -> Mon | I7: =TEXT(WEEKDAY(DATE(CalendarYear,4,7),1),"aaa") -> Tue | J7: =TEXT(WEEKDAY(DATE(CalendarYear,4,8),1),"aaa") -> Wed | K7: =TEXT(WEEKDAY(DATE(CalendarYear,4,9),1),"aaa") -> Thu | L7: =TEXT(WEEKDAY(DATE(CalendarYear,4,10),1),"aaa") -> Fri | M7: =TEXT(WEEKDAY(DATE(CalendarYear,4,11),1),"aaa") -> Sat | N7: =TEXT(WEEKDAY(DATE(CalendarYear,4,12),1),"aaa") -> Sun | O7: =TEXT(WEEKDAY(DATE(CalendarYear,4,13),1),"aaa") -> Mon | P7: =TEXT(WEEKDAY(DATE(CalendarYear,4,14),1),"aaa") -> Tue | Q7: =TEXT(WEEKDAY(DATE(CalendarYear,4,15),1),"aaa") -> Wed | R7: =TEXT(WEEKDAY(DATE(CalendarYear,4,16),1),"aaa") -> Thu | S7: =TEXT(WEEKDAY(DATE(CalendarYear,4,17),1),"aaa") -> Fri | T7: =TEXT(WEEKDAY(DATE(CalendarYear,4,18),1),"aaa") -> Sat | U7: =TEXT(WEEKDAY(DATE(CalendarYear,4,19),1),"aaa") -> Sun | V7: =TEXT(WEEKDAY(DATE(CalendarYear,4,20),1),"aaa") -> Mon | W7: =TEXT(WEEKDAY(DATE(CalendarYear,4,21),1),"aaa") -> Tue | X7: =TEXT(WEEKDAY(DATE(CalendarYear,4,22),1),"aaa") -> Wed | Y7: =TEXT(WEEKDAY(DATE(CalendarYear,4,23),1),"aaa") -> Thu | Z7: =TEXT(WEEKDAY(DATE(CalendarYear,4,24),1),"aaa") -> Fri | AA7: =TEXT(WEEKDAY(DATE(CalendarYear,4,25),1),"aaa") -> Sat | AB7: =TEXT(WEEKDAY(DATE(CalendarYear,4,26),1),"aaa") -> Sun | AC7: =TEXT(WEEKDAY(DATE(CalendarYear,4,27),1),"aaa") -> Mon | AD7: =TEXT(WEEKDAY(DATE(CalendarYear,4,28),1),"aaa") -> Tue | AE7: =TEXT(WEEKDAY(DATE(CalendarYear,4,29),1),"aaa") -> Wed | AF7: =TEXT(WEEKDAY(DATE(CalendarYear,4,30),1),"aaa") -> Thu
B8: Employee name | C8: 1 | D8: 2 | E8: 3 | F8: 4 | G8: 5 | H8: 6 | I8: 7 | J8: 8 | K8: 9 | L8: 10 | M8: 11 | N8: 12 | O8: 13 | P8: 14 | Q8: 15 | R8: 16 | S8: 17 | T8: 18 | U8: 19 | V8: 20 | W8: 21 | X8: 22 | Y8: 23 | Z8: 24 | AA8: 25 | AB8: 26 | AC8: 27 | AD8: 28 | AE8: 29 | AF8: 30 | AH8: Total days | AJ8: Amount in month | AK8: Salary | AL8: Meal | AM8: Phone | AN8: OT | AO8: Commission
B9: Mr. Somphone | C9: √ | D9: √ | E9: √ | F9: √ | G9: √ | I9: √ | J9: √ | K9: √ | L9: √ | M9: √ | N9: √ | P9: √ | Q9: √ | R9: √ | S9: √ | T9: √ | U9: √ | W9: √ | X9: √ | Y9: √ | Z9: √ | AA9: √ | AB9: √ | AD9: √ | AE9: √ | AF9: √ | AH9: =COUNTA(March5[[#This Row],[1]:[ ]]) -> 26 | AO9: =$AC$5*June[[#This Row],[Working Day]] -> 0
B10: Mss. Sunan | C10: √ | D10: √ | E10: √ | F10: √ | G10: √ | I10: √ | J10: √ | K10: √ | L10: √ | M10: √ | N10: √ | P10: √ | Q10: √ | R10: √ | S10: √ | T10: √ | U10: √ | W10: √ | X10: √ | Y10: √ | Z10: √ | AA10: √ | AB10: √ | AD10: √ | AE10: √ | AF10: √ | AH10: =COUNTA(March5[[#This Row],[1]:[ ]]) -> 26 | AJ10: =SUM(AK10:AO10) -> 5720000 | AK10: 5150000 | AL10: =March5[[#This Row],[Total days]]*AH5 -> 520000 | AM10: 50000 | AO10: =$AC$5*June[[#This Row],[Working Day]] -> 0
B11: Ms. Som | C11: √ | D11: √ | E11: √ | F11: √ | G11: √ | I11: √ | J11: √ | K11: √ | L11: √ | M11: √ | N11: √ | P11: √ | Q11: √ | R11: √ | S11: √ | T11: √ | U11: √ | W11: √ | X11: √ | Y11: √ | Z11: √ | AA11: √ | AB11: √ | AD11: √ | AE11: √ | AF11: √ | AH11: =COUNTA(March5[[#This Row],[1]:[ ]]) -> 26 | AJ11: =SUM(AK11:AO11) -> 5070000 | AK11: 4500000 | AL11: =March5[[#This Row],[Total days]]*AH5 -> 520000 | AM11: 50000 | AO11: =$AC$5*June[[#This Row],[Working Day]] -> 0
B12: Ms. Kung | C12: √ | D12: √ | E12: √ | F12: √ | G12: √ | I12: √ | J12: √ | K12: √ | L12: √ | M12: √ | N12: √ | P12: √ | Q12: √ | R12: √ | S12: √ | T12: √ | U12: √ | W12: √ | X12: √ | Y12: √ | Z12: √ | AA12: √ | AB12: √ | AD12: √ | AE12: √ | AF12: √ | AH12: =COUNTA(March5[[#This Row],[1]:[ ]]) -> 26 | AJ12: =SUM(AK12:AO12) -> 3520000 | AK12: 3000000 | AL12: =March5[[#This Row],[Total days]]*AH5 -> 520000 | AO12: =$AC$5*June[[#This Row],[Working Day]] -> 0
B13: Mr. SengAloun | C13: √ | D13: √ | E13: √ | F13: √ | G13: √ | I13: √ | J13: √ | K13: √ | L13: √ | M13: √ | N13: √ | AH13: =COUNTA(March5[[#This Row],[1]:[ ]]) -> 11 | AJ13: =SUM(AK13:AO13) -> 2123846.2 | AK13: =(4500000*March5[[#This Row],[Total days]])/AH9 -> 1903846.2 | AL13: =March5[[#This Row],[Total days]]*AH5 -> 220000 | AO13: =$AC$5*June[[#This Row],[Working Day]] -> 0
B14: Mr. Khampanh | C14: √ | D14: √ | E14: √ | F14: √ | G14: √ | I14: √ | J14: √ | K14: √ | L14: √ | M14: √ | N14: √ | AH14: =COUNTA(March5[[#This Row],[1]:[ ]]) -> 11 | AJ14: =SUM(AK14:AO14) -> 2123846.2 | AK14: =(4500000*March5[[#This Row],[Total days]])/AH9 -> 1903846.2 | AL14: =March5[[#This Row],[Total days]]*AH5 -> 220000 | AO14: =$AC$5*June[[#This Row],[Working Day]] -> 0
B15: Mr. Khounthai | C15: √ | D15: √ | E15: √ | F15: √ | G15: √ | I15: √ | J15: √ | K15: √ | L15: √ | P15: √ | Q15: √ | R15: √ | S15: √ | T15: √ | U15: √ | W15: √ | X15: √ | Y15: √ | Z15: √ | AD15: √ | AE15: √ | AF15: √ | AH15: =COUNTA(March5[[#This Row],[1]:[ ]]) -> 22 | AJ15: =SUM(AK15:AO15) -> 4720769.2 | AK15: =(5000000*March5[[#This Row],[Total days]])/AH9 -> 4230769.2 | AL15: =March5[[#This Row],[Total days]]*AH5 -> 440000 | AM15: 50000 | AO15: =$AC$5*June[[#This Row],[Working Day]] -> 0
AH16: =COUNTA(March5[[#This Row],[1]:[ ]]) -> 0 | AJ16: =SUM(AK16:AO16) -> 0 | AO16: =$AC$5*June[[#This Row],[Working Day]] -> 0
B17: =MonthName&" Total" -> Total | C17: =SUBTOTAL(103,March5[1]) -> 7 | D17: =SUBTOTAL(103,March5[2]) -> 7 | E17: =SUBTOTAL(103,March5[3]) -> 7 | F17: =SUBTOTAL(103,March5[4]) -> 7 | G17: =SUBTOTAL(103,March5[5]) -> 7 | H17: =SUBTOTAL(103,March5[6]) -> 0 | I17: =SUBTOTAL(103,March5[7]) -> 7 | J17: =SUBTOTAL(103,March5[8]) -> 7 | K17: =SUBTOTAL(103,March5[9]) -> 7 | L17: =SUBTOTAL(103,March5[10]) -> 7 | M17: =SUBTOTAL(103,March5[11]) -> 6 | N17: =SUBTOTAL(103,March5[12]) -> 6 | O17: =SUBTOTAL(103,March5[13]) -> 0 | P17: =SUBTOTAL(103,March5[14]) -> 5 | Q17: =SUBTOTAL(103,March5[15]) -> 5 | R17: =SUBTOTAL(103,March5[16]) -> 5 | S17: =SUBTOTAL(103,March5[17]) -> 5 | T17: =SUBTOTAL(103,March5[18]) -> 5 | U17: =SUBTOTAL(103,March5[19]) -> 5 | V17: =SUBTOTAL(103,March5[20]) -> 0 | W17: =SUBTOTAL(103,March5[21]) -> 5 | X17: =SUBTOTAL(103,March5[22]) -> 5 | Y17: =SUBTOTAL(103,March5[23]) -> 5 | Z17: =SUBTOTAL(103,March5[24]) -> 5 | AA17: =SUBTOTAL(103,March5[25]) -> 4 | AB17: =SUBTOTAL(103,March5[26]) -> 4 | AC17: =SUBTOTAL(103,March5[27]) -> 0 | AD17: =SUBTOTAL(103,March5[28]) -> 5 | AE17: =SUBTOTAL(103,March5[29]) -> 5 | AF17: =SUBTOTAL(109,March5[30]) -> 0 | AG17: =SUBTOTAL(109,March5[[ ]]) -> 0 | AH17: =SUBTOTAL(109,March5[Total days]) -> 148 | AJ17: =SUM(AK17:AO17) -> 0 | AO17: =$AC$5*June[[#This Row],[Working Day]] -> 0
AJ18: =SUM(AJ9:AJ17) -> 23278462

Sheet May
B1: Employee absence schedule
B2: May
AH4: Meal/day
AH5: 20000
C6: Dates of absence | AH6: =CalendarYear -> 2026
C7: =TEXT(WEEKDAY(DATE(CalendarYear,5,1),1),"aaa") -> Fri | D7: =TEXT(WEEKDAY(DATE(CalendarYear,5,2),1),"aaa") -> Sat | E7: =TEXT(WEEKDAY(DATE(CalendarYear,5,3),1),"aaa") -> Sun | F7: =TEXT(WEEKDAY(DATE(CalendarYear,5,4),1),"aaa") -> Mon | G7: =TEXT(WEEKDAY(DATE(CalendarYear,5,5),1),"aaa") -> Tue | H7: =TEXT(WEEKDAY(DATE(CalendarYear,5,6),1),"aaa") -> Wed | I7: =TEXT(WEEKDAY(DATE(CalendarYear,5,7),1),"aaa") -> Thu | J7: =TEXT(WEEKDAY(DATE(CalendarYear,5,8),1),"aaa") -> Fri | K7: =TEXT(WEEKDAY(DATE(CalendarYear,5,9),1),"aaa") -> Sat | L7: =TEXT(WEEKDAY(DATE(CalendarYear,5,10),1),"aaa") -> Sun | M7: =TEXT(WEEKDAY(DATE(CalendarYear,5,11),1),"aaa") -> Mon | N7: =TEXT(WEEKDAY(DATE(CalendarYear,5,12),1),"aaa") -> Tue | O7: =TEXT(WEEKDAY(DATE(CalendarYear,5,13),1),"aaa") -> Wed | P7: =TEXT(WEEKDAY(DATE(CalendarYear,5,14),1),"aaa") -> Thu | Q7: =TEXT(WEEKDAY(DATE(CalendarYear,5,15),1),"aaa") -> Fri | R7: =TEXT(WEEKDAY(DATE(CalendarYear,5,16),1),"aaa") -> Sat | S7: =TEXT(WEEKDAY(DATE(CalendarYear,5,17),1),"aaa") -> Sun | T7: =TEXT(WEEKDAY(DATE(CalendarYear,5,18),1),"aaa") -> Mon | U7: =TEXT(WEEKDAY(DATE(CalendarYear,5,19),1),"aaa") -> Tue | V7: =TEXT(WEEKDAY(DATE(CalendarYear,5,20),1),"aaa") -> Wed | W7: =TEXT(WEEKDAY(DATE(CalendarYear,5,21),1),"aaa") -> Thu | X7: =TEXT(WEEKDAY(DATE(CalendarYear,5,22),1),"aaa") -> Fri | Y7: =TEXT(WEEKDAY(DATE(CalendarYear,5,23),1),"aaa") -> Sat | Z7: =TEXT(WEEKDAY(DATE(CalendarYear,5,24),1),"aaa") -> Sun | AA7: =TEXT(WEEKDAY(DATE(CalendarYear,5,25),1),"aaa") -> Mon | AB7: =TEXT(WEEKDAY(DATE(CalendarYear,5,26),1),"aaa") -> Tue | AC7: =TEXT(WEEKDAY(DATE(CalendarYear,5,27),1),"aaa") -> Wed | AD7: =TEXT(WEEKDAY(DATE(CalendarYear,5,28),1),"aaa") -> Thu | AE7: =TEXT(WEEKDAY(DATE(CalendarYear,5,29),1),"aaa") -> Fri | AF7: =TEXT(WEEKDAY(DATE(CalendarYear,5,30),1),"aaa") -> Sat | AG7: =TEXT(WEEKDAY(DATE(CalendarYear,5,31),1),"aaa") -> Sun
B8: Employee name | C8: 1 | D8: 2 | E8: 3 | F8: 4 | G8: 5 | H8: 6 | I8: 7 | J8: 8 | K8: 9 | L8: 10 | M8: 11 | N8: 12 | O8: 13 | P8: 14 | Q8: 15 | R8: 16 | S8: 17 | T8: 18 | U8: 19 | V8: 20 | W8: 21 | X8: 22 | Y8: 23 | Z8: 24 | AA8: 25 | AB8: 26 | AC8: 27 | AD8: 28 | AE8: 29 | AF8: 30 | AG8: 31 | AH8: Working Day | AJ8: Amount in month | AK8: Salary | AL8: Meal | AM8: Phone | AN8: OT | AO8: Commission
B9: Mr. Somphone | C9: √ | D9: √ | E9: √ | G9: √ | H9: √ | I9: √ | J9: √ | K9: √ | L9: √ | N9: √ | O9: √ | P9: √ | Q9: √ | R9: √ | S9: √ | U9: √ | V9: √ | W9: √ | X9: √ | Y9: √ | Z9: √ | AB9: √ | AC9: √ | AD9: √ | AE9: √ | AF9: √ | AG9: √ | AH9: =COUNTA(March58[[#This Row],[1]:[31]]) -> 27 | AO9: =$AC$5*June[[#This Row],[Working Day]] -> 0
B10: Mss. Sunan | D10: √ | E10: √ | G10: √ | H10: √ | I10: √ | J10: √ | Q10: √ | R10: √ | S10: √ | U10: √ | V10: √ | W10: √ | X10: √ | Y10: √ | Z10: √ | AA10: 1 | AB10: √ | AC10: √ | AD10: √ | AE10: √ | AF10: √ | AG10: √ | AH10: =COUNTA(March58[[#This Row],[1]:[31]]) -> 22 | AJ10: =SUM(AK10:AO10) -> 5640000 | AK10: 5150000 | AL10: =March58[[#This Row],[Working Day]]*AH5 -> 440000 | AM10: 50000 | AO10: =$AC$5*June[[#This Row],[Working Day]] -> 0
B11: Mr. Tusackda | N11: √ | O11: √ | P11: √ | Q11: √ | R11: √ | S11: √ | U11: √ | V11: √ | W11: √ | X11: √ | Y11: √ | Z11: √ | AB11: √ | AC11: √ | AD11: √ | AE11: √ | AF11: √ | AG11: √ | AH11: =COUNTA(March58[[#This Row],[1]:[31]]) -> 18 | AJ11: =SUM(AK11:AO11) -> 4076666.7 | AK11: =(5500000*18)/27 -> 3666666.7 | AL11: =March58[[#This Row],[Working Day]]*AH5 -> 360000 | AM11: 50000 | AO11: =$AC$5*June[[#This Row],[Working Day]] -> 0 | AQ11: 5500000 | AR11: 27 | AS11: =March58[[#This Row],[Working Day]]*AQ11/AR11 -> 3666666.7 | AT11: =AS11+(March58[[#This Row],[Working Day]]*20000) -> 4026666.7
B12: Mss. Tor | N12: √ | O12: √ | P12: √ | Q12: √ | U12: √ | V12: √ | W12: √ | X12: √ | Y12: √ | Z12: √ | AA12: 1 | AB12: √ | AC12: √ | AD12: √ | AE12: √ | AF12: √ | AG12: √ | AH12: =COUNTA(March58[[#This Row],[1]:[31]]) -> 17 | AJ12: =SUM(AK12:AO12) -> 2593703.7 | AK12: =(3500000*17)/27 -> 2203703.7 | AL12: =March58[[#This Row],[Working Day]]*AH5 -> 340000 | AM12: 50000 | AO12: =$AC$5*June[[#This Row],[Working Day]] -> 0 | AQ12: 4000000 | AR12: 27 | AS12: =March58[[#This Row],[Working Day]]*AQ12/AR12 -> 2518518.5 | AT12: =AS12+(March58[[#This Row],[Working Day]]*20000) -> 2858518.5
B13: Mr. Add | D13: √ | E13: √ | G13: √ | H13: √ | I13: √ | J13: √ | L13: √ | N13: √ | O13: √ | P13: √ | Q13: √ | R13: √ | S13: √ | U13: √ | V13: √ | W13: √ | X13: √ | Y13: √ | Z13: √ | AB13: √ | AC13: √ | AD13: √ | AE13: √ | AF13: √ | AG13: √ | AH13: =COUNTA(March58[[#This Row],[1]:[31]]) -> 25 | AJ13: =SUM(AK13:AO13) -> 5000000 | AK13: 4500000 | AL13: =March58[[#This Row],[Working Day]]*AH5 -> 500000 | AO13: =$AC$5*June[[#This Row],[Working Day]] -> 0 | AT13: 4500000
B14: Mr. Dong | G14: √ | H14: √ | I14: √ | J14: √ | K14: √ | P14: √ | Q14: √ | V14: √ | W14: √ | X14: √ | Y14: √ | Z14: √ | AC14: √ | AD14: √ | AE14: √ | AF14: √ | AH14: =COUNTA(March58[[#This Row],[1]:[31]]) -> 16 | AJ14: =SUM(AK14:AO14) -> 4500000 | AK14: 4500000 | AO14: =$AC$5*June[[#This Row],[Working Day]] -> 0
B15: Mr. Tay | P15: √ | R15: √ | V15: √ | AH15: =COUNTA(March58[[#This Row],[1]:[31]]) -> 3 | AJ15: =SUM(AK15:AO15) -> 560000 | AK15: =(4500000*3)/27 -> 500000 | AL15: =March58[[#This Row],[Working Day]]*AH5 -> 60000 | AO15: =$AC$5*June[[#This Row],[Working Day]] -> 0 | AT15: =((4000000/27)*3)+60000 -> 504444.44
AH16: =COUNTA(March58[[#This Row],[1]:[31]]) -> 0 | AJ16: =SUM(AK16:AO16) -> 0 | AO16: =$AC$5*June[[#This Row],[Working Day]] -> 0
AH17: =COUNTA(March58[[#This Row],[1]:[31]]) -> 0 | AJ17: =SUM(AK17:AO17) -> 0 | AL17: =$AH$5*June[[#This Row],[Working Day]] -> 0 | AO17: =$AC$5*June[[#This Row],[Working Day]] -> 0
AH18: =COUNTA(March58[[#This Row],[1]:[31]]) -> 0 | AJ18: =SUM(AK18:AO18) -> 0 | AL18: =$AH$5*June[[#This Row],[Working Day]] -> 0 | AO18: =$AC$5*June[[#This Row],[Working Day]] -> 0 | AT18: 4500000
AH19: =COUNTA(March58[[#This Row],[1]:[31]]) -> 0 | AJ19: =SUM(AK19:AO19) -> 0 | AL19: =$AH$5*June[[#This Row],[Working Day]] -> 0 | AO19: =$AC$5*June[[#This Row],[Working Day]] -> 0 | AT19: =SUM(AT9:AT18) -> 16389630
B20: =MonthName&" Total" -> Total | C20: =SUBTOTAL(103,March58[1]) -> 1 | D20: =SUBTOTAL(103,March58[2]) -> 3 | E20: =SUBTOTAL(103,March58[3]) -> 3 | F20: =SUBTOTAL(103,March58[4]) -> 0 | G20: =SUBTOTAL(103,March58[5]) -> 4 | H20: =SUBTOTAL(103,March58[6]) -> 4 | I20: =SUBTOTAL(103,March58[7]) -> 4 | J20: =SUBTOTAL(103,March58[8]) -> 4 | K20: =SUBTOTAL(103,March58[9]) -> 2 | L20: =SUBTOTAL(103,March58[10]) -> 2 | M20: =SUBTOTAL(103,March58[11]) -> 0 | N20: =SUBTOTAL(103,March58[12]) -> 4 | O20: =SUBTOTAL(103,March58[13]) -> 4 | P20: =SUBTOTAL(103,March58[14]) -> 6 | Q20: =SUBTOTAL(103,March58[15]) -> 6 | R20: =SUBTOTAL(103,March58[16]) -> 5 | S20: =SUBTOTAL(103,March58[17]) -> 4 | T20: =SUBTOTAL(103,March58[18]) -> 0 | U20: =SUBTOTAL(103,March58[19]) -> 5 | V20: =SUBTOTAL(103,March58[20]) -> 7 | W20: =SUBTOTAL(103,March58[21]) -> 6 | X20: =SUBTOTAL(103,March58[22]) -> 6 | Y20: =SUBTOTAL(103,March58[23]) -> 6 | Z20: =SUBTOTAL(103,March58[24]) -> 6 | AA20: =SUBTOTAL(103,March58[25]) -> 2 | AB20: =SUBTOTAL(103,March58[26]) -> 5 | AC20: =SUBTOTAL(103,March58[27]) -> 6 | AD20: =SUBTOTAL(103,March58[28]) -> 6 | AE20: =SUBTOTAL(103,March58[29]) -> 6 | AF20: =SUBTOTAL(109,March58[30]) -> 0 | AG20: =SUBTOTAL(109,March58[31]) -> 0 | AH20: =COUNTA(June[[#This Row],[1]:[ ]]) -> 0 | AJ20: =SUM(AK20:AO20) -> 0 | AL20: =$AH$5*June[[#This Row],[Working Day]] -> 0 | AO20: =$AC$5*June[[#This Row],[Working Day]] -> 0
AH21: =COUNTA(June[[#This Row],[1]:[ ]]) -> 1 | AJ21: =SUM(AJ9:AJ20) -> 22370370
AH22: =SUBTOTAL(109,June[Working Day]) -> 130

Sheet June
B1: Employee absence schedule
B2: 45809
B4: Absence type key | C4: V | D4: Vacation | G4: A | H4: Annual leave | K4: S | L4: Sick leave | W4: Amount Commission, LAK | AC4: Amount Commission/day | AI4: Meal/day
W5: =2457210+1199485 -> 3656695 | AC5: =W5/June[[#Totals],[Working Day]] -> 28128.423 | AI5: 20000
AI6: =CalendarYear -> 2026
C7: =TEXT(WEEKDAY(DATE(CalendarYear,6,1),1),"aaa") -> Mon | D7: =TEXT(WEEKDAY(DATE(CalendarYear,6,2),1),"aaa") -> Tue | E7: =TEXT(WEEKDAY(DATE(CalendarYear,6,3),1),"aaa") -> Wed | F7: =TEXT(WEEKDAY(DATE(CalendarYear,6,4),1),"aaa") -> Thu | G7: =TEXT(WEEKDAY(DATE(CalendarYear,6,5),1),"aaa") -> Fri | H7: =TEXT(WEEKDAY(DATE(CalendarYear,6,6),1),"aaa") -> Sat | I7: =TEXT(WEEKDAY(DATE(CalendarYear,6,7),1),"aaa") -> Sun | J7: =TEXT(WEEKDAY(DATE(CalendarYear,6,8),1),"aaa") -> Mon | K7: =TEXT(WEEKDAY(DATE(CalendarYear,6,9),1),"aaa") -> Tue | L7: =TEXT(WEEKDAY(DATE(CalendarYear,6,10),1),"aaa") -> Wed | M7: =TEXT(WEEKDAY(DATE(CalendarYear,6,11),1),"aaa") -> Thu | N7: =TEXT(WEEKDAY(DATE(CalendarYear,6,12),1),"aaa") -> Fri | O7: =TEXT(WEEKDAY(DATE(CalendarYear,6,13),1),"aaa") -> Sat | P7: =TEXT(WEEKDAY(DATE(CalendarYear,6,14),1),"aaa") -> Sun | Q7: =TEXT(WEEKDAY(DATE(CalendarYear,6,15),1),"aaa") -> Mon | R7: =TEXT(WEEKDAY(DATE(CalendarYear,6,16),1),"aaa") -> Tue | S7: =TEXT(WEEKDAY(DATE(CalendarYear,6,17),1),"aaa") -> Wed | T7: =TEXT(WEEKDAY(DATE(CalendarYear,6,18),1),"aaa") -> Thu | U7: =TEXT(WEEKDAY(DATE(CalendarYear,6,19),1),"aaa") -> Fri | V7: =TEXT(WEEKDAY(DATE(CalendarYear,6,20),1),"aaa") -> Sat | W7: =TEXT(WEEKDAY(DATE(CalendarYear,6,21),1),"aaa") -> Sun | X7: =TEXT(WEEKDAY(DATE(CalendarYear,6,22),1),"aaa") -> Mon | Y7: =TEXT(WEEKDAY(DATE(CalendarYear,6,23),1),"aaa") -> Tue | Z7: =TEXT(WEEKDAY(DATE(CalendarYear,6,24),1),"aaa") -> Wed | AA7: =TEXT(WEEKDAY(DATE(CalendarYear,6,25),1),"aaa") -> Thu | AB7: =TEXT(WEEKDAY(DATE(CalendarYear,6,26),1),"aaa") -> Fri | AC7: =TEXT(WEEKDAY(DATE(CalendarYear,6,27),1),"aaa") -> Sat | AD7: =TEXT(WEEKDAY(DATE(CalendarYear,6,28),1),"aaa") -> Sun | AE7: =TEXT(WEEKDAY(DATE(CalendarYear,6,29),1),"aaa") -> Mon | AF7: =TEXT(WEEKDAY(DATE(CalendarYear,6,30),1),"aaa") -> Tue
B8: Employee name | C8: 1 | D8: 2 | E8: 3 | F8: 4 | G8: 5 | H8: 6 | I8: 7 | J8: 8 | K8: 9 | L8: 10 | M8: 11 | N8: 12 | O8: 13 | P8: 14 | Q8: 15 | R8: 16 | S8: 17 | T8: 18 | U8: 19 | V8: 20 | W8: 21 | X8: 22 | Y8: 23 | Z8: 24 | AA8: 25 | AB8: 26 | AC8: 27 | AD8: 28 | AE8: 29 | AF8: 30 | AH8: OT, day | AI8: Working Day | AK8: Amount in month | AL8: Salary | AM8: Meal | AN8: Phone | AO8: OT | AP8: Commission | AQ8: Advance Payment
B9: Mr. Somphone | C9: √ | D9: √ | E9: √ | F9: √ | G9: √ | H9: √ | I9: √ | K9: √ | L9: √ | M9: √ | N9: √ | O9: √ | P9: √ | R9: √ | S9: √ | T9: √ | U9: √ | V9: √ | W9: √ | Y9: √ | Z9: √ | AA9: √ | AB9: √ | AC9: √ | AF9: √ | AP9: =$AC$5*June[[#This Row],[Working Day]] -> 0
B10: Mss. Sunan | C10: √ | D10: √ | E10: √ | F10: √ | G10: √ | H10: √ | I10: √ | J10: √ | K10: √ | L10: √ | M10: √ | N10: √ | O10: √ | R10: √ | S10: √ | T10: √ | U10: √ | V10: √ | AI10: =COUNTA(June[[#This Row],[1]:[ ]]) -> 18 | AK10: =SUM(AL10:AP10) -> 6016311.6 | AL10: 5150000 | AM10: =$AI$5*June[[#This Row],[Working Day]] -> 360000 | AP10: =$AC$5*June[[#This Row],[Working Day]] -> 506311.62
A11: ວ0 | B11: Mr. Tusackda | C11: √ | D11: √ | E11: √ | F11: √ | G11: √ | H11: √ | I11: √ | J11: √ | K11: √ | L11: √ | M11: √ | N11: √ | O11: √ | P11: √ | R11: √ | S11: √ | T11: √ | U11: √ | V11: √ | W11: √ | Y11: √ | Z11: √ | AA11: √ | AB11: √ | AC11: √ | AF11: √ | AI11: =COUNTA(June[[#This Row],[1]:[ ]]) -> 26 | AK11: =SUM(AL11:AP11) -> 6801339 | AL11: 5500000 | AM11: =$AI$5*June[[#This Row],[Working Day]] -> 520000 | AN11: 50000 | AP11: =$AC$5*June[[#This Row],[Working Day]] -> 731339 | AQ11: 2550000
B12: Mss. Tor | C12: √ | D12: √ | E12: √ | F12: √ | G12: √ | H12: √ | I12: √ | J12: √ | K12: √ | L12: √ | M12: √ | N12: √ | O12: √ | R12: √ | S12: √ | T12: √ | U12: √ | V12: √ | Y12: √ | Z12: √ | AA12: √ | AB12: √ | AC12: √ | AF12: √ | AI12: =COUNTA(June[[#This Row],[1]:[ ]]) -> 24 | AK12: =SUM(AL12:AP12) -> 4705082.2 | AL12: 3500000 | AM12: =$AI$5*June[[#This Row],[Working Day]] -> 480000 | AN12: 50000 | AP12: =$AC$5*June[[#This Row],[Working Day]] -> 675082.15 | AQ12: 2000000
B13: Mr. Add | AI13: =COUNTA(June[[#This Row],[1]:[ ]]) -> 0 | AK13: =SUM(AL13:AP13) -> 0 | AM13: =$AI$5*June[[#This Row],[Working Day]] -> 0 | AP13: =$AC$5*June[[#This Row],[Working Day]] -> 0
B14: Mr. Vone | D14: √ | E14: √ | F14: √ | G14: √ | H14: √ | I14: √ | K14: √ | L14: √ | M14: √ | N14: √ | O14: √ | P14: √ | R14: √ | S14: √ | T14: √ | U14: √ | V14: √ | W14: √ | Y14: √ | Z14: √ | AA14: √ | AB14: √ | AC14: √ | AI14: =COUNTA(June[[#This Row],[1]:[ ]]) -> 23 | AK14: =SUM(AL14:AP14) -> 6306953.7 | AL14: 5150000 | AM14: =$AI$5*June[[#This Row],[Working Day]] -> 460000 | AN14: 50000 | AP14: =$AC$5*June[[#This Row],[Working Day]] -> 646953.73
B15: Mr. Tay | D15: √ | E15: √ | F15: √ | G15: √ | I15: √ | K15: √ | L15: √ | M15: √ | N15: √ | O15: √ | P15: √ | R15: √ | S15: √ | T15: √ | U15: √ | W15: √ | Y15: √ | Z15: √ | AA15: √ | AB15: √ | AC15: √ | AF15: √ | AI15: =COUNTA(June[[#This Row],[1]:[ ]]) -> 22 | AK15: =SUM(AL15:AP15) -> 5608825.3 | AL15: 4500000 | AM15: =$AI$5*June[[#This Row],[Working Day]] -> 440000 | AN15: 50000 | AP15: =$AC$5*June[[#This Row],[Working Day]] -> 618825.31 | AQ15: 1000000
B16: Mr.Berd | K16: √ | L16: √ | M16: √ | N16: √ | O16: √ | P16: √ | R16: √ | S16: √ | T16: √ | U16: √ | V16: √ | Y16: √ | Z16: √ | AA16: √ | AB16: √ | AC16: √ | AF16: √ | AI16: =COUNTA(June[[#This Row],[1]:[ ]]) -> 17 | AK16: =SUM(AL16:AP16) -> 3538183.2 | AL16: =(4000000*17)/25 -> 2720000 | AM16: =$AI$5*June[[#This Row],[Working Day]] -> 340000 | AP16: =$AC$5*June[[#This Row],[Working Day]] -> 478183.19 | AQ16: 500000
AI17: =COUNTA(June[[#This Row],[1]:[ ]]) -> 0 | AK17: =SUM(AL17:AP17) -> 0 | AM17: =$AI$5*June[[#This Row],[Working Day]] -> 0 | AP17: =$AC$5*June[[#This Row],[Working Day]] -> 0
AI18: =COUNTA(June[[#This Row],[1]:[ ]]) -> 0 | AK18: =SUM(AL18:AP18) -> 0 | AM18: =$AI$5*June[[#This Row],[Working Day]] -> 0 | AP18: =$AC$5*June[[#This Row],[Working Day]] -> 0
AI19: =COUNTA(June[[#This Row],[1]:[ ]]) -> 0 | AK19: =SUM(AL19:AP19) -> 0 | AM19: =$AI$5*June[[#This Row],[Working Day]] -> 0 | AP19: =$AC$5*June[[#This Row],[Working Day]] -> 0
AI20: =COUNTA(June[[#This Row],[1]:[ ]]) -> 0 | AK20: =SUM(AL20:AP20) -> 0 | AM20: =$AI$5*June[[#This Row],[Working Day]] -> 0 | AP20: =$AC$5*June[[#This Row],[Working Day]] -> 0
B21: =MonthName&" Total" -> 45809 Total | C21: =SUBTOTAL(103,June[1]) -> 4 | D21: =SUBTOTAL(103,June[2]) -> 6 | E21: =SUBTOTAL(103,June[3]) -> 6 | F21: =SUBTOTAL(103,June[4]) -> 6 | G21: =SUBTOTAL(103,June[5]) -> 6 | H21: =SUBTOTAL(103,June[6]) -> 5 | I21: =SUBTOTAL(103,June[7]) -> 6 | J21: =SUBTOTAL(103,June[8]) -> 3 | K21: =SUBTOTAL(103,June[9]) -> 7 | L21: =SUBTOTAL(103,June[10]) -> 7 | M21: =SUBTOTAL(103,June[11]) -> 7 | N21: =SUBTOTAL(103,June[12]) -> 7 | O21: =SUBTOTAL(103,June[13]) -> 7 | P21: =SUBTOTAL(103,June[14]) -> 5 | Q21: =SUBTOTAL(103,June[15]) -> 0 | R21: =SUBTOTAL(103,June[16]) -> 7 | S21: =SUBTOTAL(103,June[17]) -> 7 | T21: =SUBTOTAL(103,June[18]) -> 7 | U21: =SUBTOTAL(103,June[19]) -> 7 | V21: =SUBTOTAL(103,June[20]) -> 6 | W21: =SUBTOTAL(103,June[21]) -> 4 | X21: =SUBTOTAL(103,June[22]) -> 0 | Y21: =SUBTOTAL(103,June[23]) -> 6 | Z21: =SUBTOTAL(103,June[24]) -> 6 | AA21: =SUBTOTAL(103,June[25]) -> 6 | AB21: =SUBTOTAL(103,June[26]) -> 6 | AC21: =SUBTOTAL(103,June[27]) -> 6 | AD21: =SUBTOTAL(103,June[28]) -> 0 | AE21: =SUBTOTAL(103,June[29]) -> 0 | AF21: =SUBTOTAL(109,June[30]) -> 0 | AG21: =SUBTOTAL(109,June[[ ]]) -> 0 | AI21: =SUBTOTAL(109,June[Working Day]) -> 130 | AK21: =SUM(AK9:AK20) -> 32976695
AK27: 7.0064455e+08

Sheet July
B1: Employee absence schedule
B2: July
B4: Absence type key | C4: V | D4: Vacation | G4: A | H4: Annual leave | K4: S | L4: Sick leave | W4: Amount Commission, LAK | AC4: Amount Commission/day | AI4: Meal/day
W5: =1859165+2780745 -> 4639910 | AC5: =W5/July[[#Totals],[Total days]] -> 43772.736 | AI5: 20000
C6: Dates of absence | AH6: =CalendarYear -> 2026
C7: =TEXT(WEEKDAY(DATE(CalendarYear,7,1),1),"aaa") -> Wed | D7: =TEXT(WEEKDAY(DATE(CalendarYear,7,2),1),"aaa") -> Thu | E7: =TEXT(WEEKDAY(DATE(CalendarYear,7,3),1),"aaa") -> Fri | F7: =TEXT(WEEKDAY(DATE(CalendarYear,7,4),1),"aaa") -> Sat | G7: =TEXT(WEEKDAY(DATE(CalendarYear,7,5),1),"aaa") -> Sun | H7: =TEXT(WEEKDAY(DATE(CalendarYear,7,6),1),"aaa") -> Mon | I7: =TEXT(WEEKDAY(DATE(CalendarYear,7,7),1),"aaa") -> Tue | J7: =TEXT(WEEKDAY(DATE(CalendarYear,7,8),1),"aaa") -> Wed | K7: =TEXT(WEEKDAY(DATE(CalendarYear,7,9),1),"aaa") -> Thu | L7: =TEXT(WEEKDAY(DATE(CalendarYear,7,10),1),"aaa") -> Fri | M7: =TEXT(WEEKDAY(DATE(CalendarYear,7,11),1),"aaa") -> Sat | N7: =TEXT(WEEKDAY(DATE(CalendarYear,7,12),1),"aaa") -> Sun | O7: =TEXT(WEEKDAY(DATE(CalendarYear,7,13),1),"aaa") -> Mon | P7: =TEXT(WEEKDAY(DATE(CalendarYear,7,14),1),"aaa") -> Tue | Q7: =TEXT(WEEKDAY(DATE(CalendarYear,7,15),1),"aaa") -> Wed | R7: =TEXT(WEEKDAY(DATE(CalendarYear,7,16),1),"aaa") -> Thu | S7: =TEXT(WEEKDAY(DATE(CalendarYear,7,17),1),"aaa") -> Fri | T7: =TEXT(WEEKDAY(DATE(CalendarYear,7,18),1),"aaa") -> Sat | U7: =TEXT(WEEKDAY(DATE(CalendarYear,7,19),1),"aaa") -> Sun | V7: =TEXT(WEEKDAY(DATE(CalendarYear,7,20),1),"aaa") -> Mon | W7: =TEXT(WEEKDAY(DATE(CalendarYear,7,21),1),"aaa") -> Tue | X7: =TEXT(WEEKDAY(DATE(CalendarYear,7,22),1),"aaa") -> Wed | Y7: =TEXT(WEEKDAY(DATE(CalendarYear,7,23),1),"aaa") -> Thu | Z7: =TEXT(WEEKDAY(DATE(CalendarYear,7,24),1),"aaa") -> Fri | AA7: =TEXT(WEEKDAY(DATE(CalendarYear,7,25),1),"aaa") -> Sat | AB7: =TEXT(WEEKDAY(DATE(CalendarYear,7,26),1),"aaa") -> Sun | AC7: =TEXT(WEEKDAY(DATE(CalendarYear,7,27),1),"aaa") -> Mon | AD7: =TEXT(WEEKDAY(DATE(CalendarYear,7,28),1),"aaa") -> Tue | AE7: =TEXT(WEEKDAY(DATE(CalendarYear,7,29),1),"aaa") -> Wed | AF7: =TEXT(WEEKDAY(DATE(CalendarYear,7,30),1),"aaa") -> Thu | AG7: =TEXT(WEEKDAY(DATE(CalendarYear,7,31),1),"aaa") -> Fri
B8: Employee name | C8: 1 | D8: 2 | E8: 3 | F8: 4 | G8: 5 | H8: 6 | I8: 7 | J8: 8 | K8: 9 | L8: 10 | M8: 11 | N8: 12 | O8: 13 | P8: 14 | Q8: 15 | R8: 16 | S8: 17 | T8: 18 | U8: 19 | V8: 20 | W8: 21 | X8: 22 | Y8: 23 | Z8: 24 | AA8: 25 | AB8: 26 | AC8: 27 | AD8: 28 | AE8: 29 | AF8: 30 | AG8: 31 | AH8: Total days | AK8: Amount in month | AL8: Salary | AM8: Meal | AN8: Phone | AO8: incentive | AP8: Commission | AQ8: Advance | AR8: Date
B9: Mr. Somphone | C9: √ | D9: √ | E9: √ | F9: √ | G9: √ | I9: √ | J9: √ | K9: √ | M9: √ | N9: √ | P9: √ | Q9: √ | R9: √ | S9: √ | T9: √ | U9: √ | W9: √ | X9: √ | Y9: √ | AA9: √ | AB9: √ | AD9: √ | AE9: √ | AF9: √ | AG9: √ | AP9: =$AC$5*June[[#This Row],[Working Day]] -> 0
B10: Mr. Tay | C10: √ | D10: √ | E10: √ | F10: √ | G10: √ | H10: √ | J10: √ | K10: √ | M10: √ | N10: √ | Q10: √ | R10: √ | S10: √ | T10: √ | U10: √ | W10: √ | X10: √ | Y10: √ | AA10: √ | AB10: √ | AD10: √ | AE10: √ | AF10: √ | AG10: √ | AH10: =COUNTA(July[[#This Row],[1]:[31]]) -> 24 | AK10: =SUM(AL10:AP10) -> 6080545.7 | AL10: 4500000 | AM10: =$AI$5*July[[#This Row],[Total days]] -> 480000 | AN10: 50000 | AP10: =AC5*July[[#This Row],[Total days]] -> 1050545.7
B11: Mr. Tusackda | C11: √ | D11: √ | E11: √ | F11: √ | G11: √ | H11: √ | I11: √ | J11: √ | K11: √ | M11: √ | N11: √ | P11: √ | Q11: √ | R11: √ | S11: √ | U11: √ | W11: √ | X11: √ | Y11: √ | AA11: √ | AB11: √ | AD11: √ | AE11: √ | AF11: √ | AG11: √ | AH11: =COUNTA(July[[#This Row],[1]:[31]]) -> 25 | AI11: 7 | AK11: =SUM(AL11:AP11) -> 7144318.4 | AL11: 5500000 | AM11: =$AI$5*July[[#This Row],[Total days]] -> 500000 | AN11: 50000 | AP11: =AC5*July[[#This Row],[Total days]] -> 1094318.4
B12: Mss. Tor | C12: √ | D12: √ | E12: √ | F12: √ | G12: √ | J12: √ | K12: √ | Q12: √ | R12: √ | S12: √ | U12: √ | W12: √ | X12: √ | Y12: √ | AA12: √ | AB12: √ | AD12: √ | AE12: √ | AF12: √ | AG12: √ | AH12: =COUNTA(July[[#This Row],[1]:[31]]) -> 20 | AK12: =SUM(AL12:AP12) -> 5325454.7 | AL12: 4000000 | AM12: =$AI$5*July[[#This Row],[Total days]] -> 400000 | AN12: 50000 | AP12: =AC5*July[[#This Row],[Total days]] -> 875454.72 | AQ12: 1000000 | AR12: 45859
B13: Mr. Vone | C13: √ | D13: √ | E13: √ | F13: √ | G13: √ | H13: √ | I13: √ | J13: √ | K13: √ | N13: √ | Q13: √ | R13: √ | S13: √ | T13: √ | U13: √ | W13: √ | X13: √ | Y13: √ | AA13: √ | AB13: √ | AD13: √ | AE13: √ | AF13: √ | AG13: √ | AH13: =COUNTA(July[[#This Row],[1]:[31]]) -> 24 | AK13: =SUM(AL13:AP13) -> 6730545.7 | AL13: 5150000 | AM13: =$AI$5*July[[#This Row],[Total days]] -> 480000 | AN13: 50000 | AP13: =AC5*July[[#This Row],[Total days]] -> 1050545.7
B14: Ms. Som | Q14: √ | R14: √ | S14: √ | U14: √ | W14: √ | X14: √ | Y14: √ | AA14: √ | AB14: √ | AD14: √ | AE14: √ | AF14: √ | AG14: √ | AH14: =COUNTA(July[[#This Row],[1]:[31]]) -> 13 | AK14: =SUM(AL14:AP14) -> 3169045.6 | AL14: =(4500000*13)/25 -> 2340000 | AM14: =$AI$5*July[[#This Row],[Total days]] -> 260000 | AP14: =AC5*July[[#This Row],[Total days]] -> 569045.57
AH15: =COUNTA(July[[#This Row],[1]:[31]]) -> 0 | AK15: =SUM(AL15:AP15) -> 0 | AM15: =$AI$5*July[[#This Row],[Total days]] -> 0 | AP15: =AC9*July[[#This Row],[Total days]] -> 0
AH16: =COUNTA(July[[#This Row],[1]:[31]]) -> 0 | AK16: =SUM(AL16:AP16) -> 0 | AM16: =$AI$5*July[[#This Row],[Total days]] -> 0 | AP16: =AC10*July[[#This Row],[Total days]] -> 0
AH17: =COUNTA(July[[#This Row],[1]:[31]]) -> 0 | AK17: =SUM(AL17:AP17) -> 0 | AM17: =$AI$5*July[[#This Row],[Total days]] -> 0 | AP17: =$AC$5*June[[#This Row],[Working Day]] -> 0
B18: =MonthName&" Total" -> July Total | C18: =SUBTOTAL(103,July[1]) -> 5 | D18: =SUBTOTAL(103,July[2]) -> 5 | E18: =SUBTOTAL(103,July[3]) -> 5 | F18: =SUBTOTAL(103,July[4]) -> 5 | G18: =SUBTOTAL(103,July[5]) -> 5 | H18: =SUBTOTAL(103,July[6]) -> 3 | I18: =SUBTOTAL(103,July[7]) -> 3 | J18: =SUBTOTAL(103,July[8]) -> 5 | K18: =SUBTOTAL(103,July[9]) -> 5 | L18: =SUBTOTAL(103,July[10]) -> 0 | M18: =SUBTOTAL(103,July[11]) -> 3 | N18: =SUBTOTAL(103,July[12]) -> 4 | O18: =SUBTOTAL(103,July[13]) -> 0 | P18: =SUBTOTAL(103,July[14]) -> 2 | Q18: =SUBTOTAL(103,July[15]) -> 6 | R18: =SUBTOTAL(103,July[16]) -> 6 | S18: =SUBTOTAL(103,July[17]) -> 6 | T18: =SUBTOTAL(103,July[18]) -> 3 | U18: =SUBTOTAL(103,July[19]) -> 6 | V18: =SUBTOTAL(103,July[20]) -> 0 | W18: =SUBTOTAL(103,July[21]) -> 6 | X18: =SUBTOTAL(103,July[22]) -> 6 | Y18: =SUBTOTAL(103,July[23]) -> 6 | Z18: =SUBTOTAL(103,July[24]) -> 0 | AA18: =SUBTOTAL(103,July[25]) -> 6 | AB18: =SUBTOTAL(103,July[26]) -> 6 | AC18: =SUBTOTAL(103,July[27]) -> 0 | AD18: =SUBTOTAL(103,July[28]) -> 6 | AE18: =SUBTOTAL(103,July[29]) -> 6 | AF18: =SUBTOTAL(109,July[30]) -> 0 | AG18: =SUBTOTAL(109,July[31]) -> 0 | AH18: =SUBTOTAL(109,July[Total days]) -> 106 | AK18: =SUM(AK9:AK17) -> 28449910 | AL18: =SUM(AL9:AL17) -> 21490000 | AM18: =SUM(AM9:AM17) -> 2120000 | AN18: =SUM(AN9:AN17) -> 200000 | AO18: =SUM(AO9:AO17) -> 0 | AP18: =SUM(AP9:AP17) -> 4639910 | AQ18: =SUM(AQ9:AQ17) -> 1000000

Sheet August
B1: Employee absence schedule
B2: August
B4: Absence type key | C4: V | D4: Vacation | G4: A | H4: Annual leave | K4: S | L4: Sick leave | P4: Holiday | T4: Absent without reason | W4: Amount Commission, LAK | AC4: Amount Commission/day | AI4: Meal/day
W5: =2408370+1421725 -> 3830095 | AC5: =W5/August[[#Totals],[Total days]] -> 35795.28 | AI5: 20000
C6: Dates of absence | AH6: =CalendarYear -> 2026
C7: =TEXT(WEEKDAY(DATE(CalendarYear,8,1),1),"aaa") -> Sat | D7: =TEXT(WEEKDAY(DATE(CalendarYear,8,2),1),"aaa") -> Sun | E7: =TEXT(WEEKDAY(DATE(CalendarYear,8,3),1),"aaa") -> Mon | F7: =TEXT(WEEKDAY(DATE(CalendarYear,8,4),1),"aaa") -> Tue | G7: =TEXT(WEEKDAY(DATE(CalendarYear,8,5),1),"aaa") -> Wed | H7: =TEXT(WEEKDAY(DATE(CalendarYear,8,6),1),"aaa") -> Thu | I7: =TEXT(WEEKDAY(DATE(CalendarYear,8,7),1),"aaa") -> Fri | J7: =TEXT(WEEKDAY(DATE(CalendarYear,8,8),1),"aaa") -> Sat | K7: =TEXT(WEEKDAY(DATE(CalendarYear,8,9),1),"aaa") -> Sun | L7: =TEXT(WEEKDAY(DATE(CalendarYear,8,10),1),"aaa") -> Mon | M7: =TEXT(WEEKDAY(DATE(CalendarYear,8,11),1),"aaa") -> Tue | N7: =TEXT(WEEKDAY(DATE(CalendarYear,8,12),1),"aaa") -> Wed | O7: =TEXT(WEEKDAY(DATE(CalendarYear,8,13),1),"aaa") -> Thu | P7: =TEXT(WEEKDAY(DATE(CalendarYear,8,14),1),"aaa") -> Fri | Q7: =TEXT(WEEKDAY(DATE(CalendarYear,8,15),1),"aaa") -> Sat | R7: =TEXT(WEEKDAY(DATE(CalendarYear,8,16),1),"aaa") -> Sun | S7: =TEXT(WEEKDAY(DATE(CalendarYear,8,17),1),"aaa") -> Mon | T7: =TEXT(WEEKDAY(DATE(CalendarYear,8,18),1),"aaa") -> Tue | U7: =TEXT(WEEKDAY(DATE(CalendarYear,8,19),1),"aaa") -> Wed | V7: =TEXT(WEEKDAY(DATE(CalendarYear,8,20),1),"aaa") -> Thu | W7: =TEXT(WEEKDAY(DATE(CalendarYear,8,21),1),"aaa") -> Fri | X7: =TEXT(WEEKDAY(DATE(CalendarYear,8,22),1),"aaa") -> Sat | Y7: =TEXT(WEEKDAY(DATE(CalendarYear,8,23),1),"aaa") -> Sun | Z7: =TEXT(WEEKDAY(DATE(CalendarYear,8,24),1),"aaa") -> Mon | AA7: =TEXT(WEEKDAY(DATE(CalendarYear,8,25),1),"aaa") -> Tue | AB7: =TEXT(WEEKDAY(DATE(CalendarYear,8,26),1),"aaa") -> Wed | AC7: =TEXT(WEEKDAY(DATE(CalendarYear,8,27),1),"aaa") -> Thu | AD7: =TEXT(WEEKDAY(DATE(CalendarYear,8,28),1),"aaa") -> Fri | AE7: =TEXT(WEEKDAY(DATE(CalendarYear,8,29),1),"aaa") -> Sat | AF7: =TEXT(WEEKDAY(DATE(CalendarYear,8,30),1),"aaa") -> Sun | AG7: =TEXT(WEEKDAY(DATE(CalendarYear,8,31),1),"aaa") -> Mon
B8: Employee name | C8: 1 | D8: 2 | E8: 3 | F8: 4 | G8: 5 | H8: 6 | I8: 7 | J8: 8 | K8: 9 | L8: 10 | M8: 11 | N8: 12 | O8: 13 | P8: 14 | Q8: 15 | R8: 16 | S8: 17 | T8: 18 | U8: 19 | V8: 20 | W8: 21 | X8: 22 | Y8: 23 | Z8: 24 | AA8: 25 | AB8: 26 | AC8: 27 | AD8: 28 | AE8: 29 | AF8: 30 | AG8: 31 | AH8: Total days | AK8: Amount in month | AL8: Salary | AM8: Meal | AN8: Phone | AO8: incentive | AP8: Commission
B9: Mr. Somphone | C9: √ | F9: √ | G9: √ | H9: √ | I9: √ | J9: √ | K9: √ | M9: √ | N9: √ | O9: √ | P9: √ | Q9: √ | R9: √ | T9: √ | U9: √ | V9: √ | W9: √ | X9: √ | Y9: √ | AA9: √ | AB9: √ | AC9: √ | AD9: √ | AE9: √ | AF9: √ | AP9: =$AC$5*June[[#This Row],[Working Day]] -> 0
B10: Mr. Tay | C10: √ | F10: √ | G10: √ | H10: √ | I10: √ | N10: √ | O10: √ | P10: √ | Q10: √ | U10: √ | V10: √ | W10: √ | X10: √ | AH10: =COUNTA(August[[#This Row],[1]:[31]]) -> 13 | AK10: =SUM(AL10:AP10) -> 5375338.6 | AL10: 4500000 | AM10: =$AI$5*August[[#This Row],[Total days]] -> 260000 | AN10: 50000 | AP10: =($AC$5*August[[#This Row],[Total days]])+100000 -> 565338.64
B11: Mr. Tusackda | C11: √ | F11: √ | G11: √ | H11: √ | I11: √ | J11: √ | M11: √ | N11: √ | O11: √ | P11: √ | Q11: √ | R11: √ | T11: √ | U11: √ | V11: √ | W11: √ | X11: √ | Y11: √ | AA11: √ | AB11: √ | AC11: √ | AD11: √ | AE11: √ | AF11: √ | AH11: =COUNTA(August[[#This Row],[1]:[31]]) -> 24 | AK11: =SUM(AL11:AP11) -> 6889086.7 | AL11: 5500000 | AM11: =$AI$5*August[[#This Row],[Total days]] -> 480000 | AN11: 50000 | AP11: =$AC$5*August[[#This Row],[Total days]] -> 859086.73
B12: Mss. Tor | C12: √ | D12: √ | F12: √ | G12: √ | H12: √ | I12: √ | J12: √ | M12: √ | N12: √ | O12: √ | P12: √ | Q12: √ | T12: √ | U12: √ | V12: √ | W12: √ | X12: √ | AA12: √ | AB12: √ | AC12: √ | AD12: √ | AE12: √ | AH12: =COUNTA(August[[#This Row],[1]:[31]]) -> 22 | AK12: =SUM(AL12:AP12) -> 5377496.2 | AL12: 4100000 | AM12: =$AI$5*August[[#This Row],[Total days]] -> 440000 | AN12: 50000 | AP12: =$AC$5*August[[#This Row],[Total days]] -> 787496.17
B13: Mr. Vone | C13: √ | D13: √ | F13: √ | H13: √ | I13: √ | J13: √ | K13: √ | M13: √ | N13: √ | O13: √ | P13: √ | Q13: √ | R13: √ | T13: √ | U13: √ | V13: √ | W13: √ | X13: √ | Y13: √ | AA13: √ | AB13: √ | AC13: √ | AD13: √ | AE13: √ | AF13: √ | AH13: =COUNTA(August[[#This Row],[1]:[31]]) -> 25 | AK13: =SUM(AL13:AP13) -> 6394882 | AL13: 5000000 | AM13: =$AI$5*August[[#This Row],[Total days]] -> 500000 | AN13: 50000 | AP13: =($AC$5*August[[#This Row],[Total days]])-50000 -> 844882.01
B14: Ms. Som | C14: √ | D14: √ | F14: √ | G14: √ | H14: √ | I14: √ | J14: √ | K14: √ | M14: √ | N14: √ | O14: √ | P14: √ | Q14: √ | T14: √ | U14: √ | V14: √ | W14: √ | X14: √ | AA14: √ | AB14: √ | AC14: √ | AD14: √ | AE14: √ | AH14: =COUNTA(August[[#This Row],[1]:[31]]) -> 23 | AK14: =SUM(AL14:AP14) -> 5483291.4 | AL14: 4200000 | AM14: =$AI$5*August[[#This Row],[Total days]] -> 460000 | AN14: 50000 | AP14: =($AC$5*August[[#This Row],[Total days]])-50000 -> 773291.45 | AQ14: 5000000
AH15: =COUNTA(August[[#This Row],[1]:[31]]) -> 0
C16: =SUBTOTAL(103,August[1]) -> 6 | D16: =SUBTOTAL(103,August[2]) -> 3 | E16: =SUBTOTAL(103,August[3]) -> 0 | F16: =SUBTOTAL(103,August[4]) -> 6 | G16: =SUBTOTAL(103,August[5]) -> 5 | H16: =SUBTOTAL(103,August[6]) -> 6 | I16: =SUBTOTAL(103,August[7]) -> 6 | J16: =SUBTOTAL(103,August[8]) -> 5 | K16: =SUBTOTAL(103,August[9]) -> 3 | L16: =SUBTOTAL(103,August[10]) -> 0 | M16: =SUBTOTAL(103,August[11]) -> 5 | N16: =SUBTOTAL(103,August[12]) -> 6 | O16: =SUBTOTAL(103,August[13]) -> 6 | P16: =SUBTOTAL(103,August[14]) -> 6 | Q16: =SUBTOTAL(103,August[15]) -> 6 | R16: =SUBTOTAL(103,August[16]) -> 3 | S16: =SUBTOTAL(103,August[17]) -> 0 | T16: =SUBTOTAL(103,August[18]) -> 5 | U16: =SUBTOTAL(103,August[19]) -> 6 | V16: =SUBTOTAL(103,August[20]) -> 6 | W16: =SUBTOTAL(103,August[21]) -> 6 | X16: =SUBTOTAL(103,August[22]) -> 6 | Y16: =SUBTOTAL(103,August[23]) -> 3 | Z16: =SUBTOTAL(103,August[24]) -> 0 | AA16: =SUBTOTAL(103,August[25]) -> 5 | AB16: =SUBTOTAL(103,August[26]) -> 5 | AC16: =SUBTOTAL(103,August[27]) -> 5 | AD16: =SUBTOTAL(103,August[28]) -> 5 | AE16: =SUBTOTAL(103,August[29]) -> 5 | AF16: =SUBTOTAL(109,August[30]) -> 0 | AG16: =SUBTOTAL(109,August[31]) -> 0 | AH16: =SUBTOTAL(109,August[Total days]) -> 107 | AK16: =SUM(AK9:AK14) -> 29520095 | AL16: =SUM(AL9:AL14) -> 23300000 | AM16: =SUM(AM9:AM14) -> 2140000 | AN16: =SUM(AN9:AN14) -> 250000 | AO16: =SUM(AO9:AO14) -> 0 | AP16: =SUM(AP9:AP14) -> 3830095
B18: incentive: | C18: ແຮງຈູງໃຈແມ່ນບາງສິ່ງບາງຢ່າງທີ່ກະຕຸ້ນໃຫ້ທ່ານປະຕິບັດຫຼືເຮັດວຽກຫນັກ.
C19: 1. Personalized gifts The most encouraging rewards are ones tailored to an individual and their interests. By creating personalized gifts, organizations make employees feel special. Personal sales incentives include gift cards that align with a recipient’s hobbies, personalized office accessories or mementos, and recognition awards engraved with details of the honoree’s achievement.
C21: 2. Professional development Professional development is an extremely important asset that job seekers and staff members look for. When made into sales incentives, development opportunities can be created for individuals or teams. For instance, top-performing salespeople can attend a seminar, conference, or classes. Also, high achievers can be granted membership to elite groups dedicated to different fields or industries.
C23: 3. Office gadgets Whether used to ramp up corporate or home offices, tech gadgets and other tools can help improve employee productivity. These items make great sales incentives because they offer staff many benefits. From making team members more comfortable to helping them stay organized, these gadgets help individuals and the whole organization. Examples include a standing desk, headphones, and personalized paper weights.
C25: 4. Event tickets Tickets to special events are exciting for competitive employees. Whether a once-in-a-lifetime occasion or a fun night on the town, unique events inspire staff to work harder. For instance, a business can give tickets to concerts, sporting events, fundraisers, award shows, cooking classes, and more.
C27: 5. Company benefits In the eyes of staff members, company benefits are highly valuable. Many employees would become more engaged and productive if given the chance to earn added paid time off or a VIP parking spot. Other sought-after benefits include discounts and retirement plans.
C29: 6. Cash incentives Cash incentives offer a straightforward, quantifiable reward that directly impacts an employee’s income. They are typically given in the form of commissions, bonuses, or profit-sharing, enabling salespeople to earn more by selling more. Cash rewards as a sales incentive provides immediate gratification, which can be a strong driver or short-term sales boosts.
C31: 7. Flexible work arrangements Flexible work arrangements are becoming an increasingly attractive sales incentive, recognizing the diverse needs and employees’ personal work-life balance preferences. Such arrangements can include options like flexible work hours, compressed workweeks or working from home, encouraging a better work-life balance. This modern approach to structuring work can lead to heightened job satisfaction, lower stress levels, and increased loyalty to the company.

Sheet September
B1: Employee absence schedule
B2: September
B4: Absence type key | C4: V | D4: Vacation | G4: A | H4: Annual leave | K4: S | L4: Sick leave | P4: Holiday | T4: Absent without reason | W4: Amount Commission, LAK | AC4: Amount Commission/day | AI4: Meal/day
W5: =1532175+1605075 -> 3137250 | AC5: =W5/September[[#Totals],[Total days]] -> 23948.473 | AI5: 20000
C6: Dates of absence | AH6: =CalendarYear -> 2026
C7: =TEXT(WEEKDAY(DATE(CalendarYear,9,1),1),"aaa") -> Tue | D7: =TEXT(WEEKDAY(DATE(CalendarYear,9,2),1),"aaa") -> Wed | E7: =TEXT(WEEKDAY(DATE(CalendarYear,9,3),1),"aaa") -> Thu | F7: =TEXT(WEEKDAY(DATE(CalendarYear,9,4),1),"aaa") -> Fri | G7: =TEXT(WEEKDAY(DATE(CalendarYear,9,5),1),"aaa") -> Sat | H7: =TEXT(WEEKDAY(DATE(CalendarYear,9,6),1),"aaa") -> Sun | I7: =TEXT(WEEKDAY(DATE(CalendarYear,9,7),1),"aaa") -> Mon | J7: =TEXT(WEEKDAY(DATE(CalendarYear,9,8),1),"aaa") -> Tue | K7: =TEXT(WEEKDAY(DATE(CalendarYear,9,9),1),"aaa") -> Wed | L7: =TEXT(WEEKDAY(DATE(CalendarYear,9,10),1),"aaa") -> Thu | M7: =TEXT(WEEKDAY(DATE(CalendarYear,9,11),1),"aaa") -> Fri | N7: =TEXT(WEEKDAY(DATE(CalendarYear,9,12),1),"aaa") -> Sat | O7: =TEXT(WEEKDAY(DATE(CalendarYear,9,13),1),"aaa") -> Sun | P7: =TEXT(WEEKDAY(DATE(CalendarYear,9,14),1),"aaa") -> Mon | Q7: =TEXT(WEEKDAY(DATE(CalendarYear,9,15),1),"aaa") -> Tue | R7: =TEXT(WEEKDAY(DATE(CalendarYear,9,16),1),"aaa") -> Wed | S7: =TEXT(WEEKDAY(DATE(CalendarYear,9,17),1),"aaa") -> Thu | T7: =TEXT(WEEKDAY(DATE(CalendarYear,9,18),1),"aaa") -> Fri | U7: =TEXT(WEEKDAY(DATE(CalendarYear,9,19),1),"aaa") -> Sat | V7: =TEXT(WEEKDAY(DATE(CalendarYear,9,20),1),"aaa") -> Sun | W7: =TEXT(WEEKDAY(DATE(CalendarYear,9,21),1),"aaa") -> Mon | X7: =TEXT(WEEKDAY(DATE(CalendarYear,9,22),1),"aaa") -> Tue | Y7: =TEXT(WEEKDAY(DATE(CalendarYear,9,23),1),"aaa") -> Wed | Z7: =TEXT(WEEKDAY(DATE(CalendarYear,9,24),1),"aaa") -> Thu | AA7: =TEXT(WEEKDAY(DATE(CalendarYear,9,25),1),"aaa") -> Fri | AB7: =TEXT(WEEKDAY(DATE(CalendarYear,9,26),1),"aaa") -> Sat | AC7: =TEXT(WEEKDAY(DATE(CalendarYear,9,27),1),"aaa") -> Sun | AD7: =TEXT(WEEKDAY(DATE(CalendarYear,9,28),1),"aaa") -> Mon | AE7: =TEXT(WEEKDAY(DATE(CalendarYear,9,29),1),"aaa") -> Tue | AF7: =TEXT(WEEKDAY(DATE(CalendarYear,9,30),1),"aaa") -> Wed
B8: Employee name | C8: 1 | D8: 2 | E8: 3 | F8: 4 | G8: 5 | H8: 6 | I8: 7 | J8: 8 | K8: 9 | L8: 10 | M8: 11 | N8: 12 | O8: 13 | P8: 14 | Q8: 15 | R8: 16 | S8: 17 | T8: 18 | U8: 19 | V8: 20 | W8: 21 | X8: 22 | Y8: 23 | Z8: 24 | AA8: 25 | AB8: 26 | AC8: 27 | AD8: 28 | AE8: 29 | AF8: 30 | AH8: Total days | AK8: Amount in month | AL8: Salary | AM8: Meal | AN8: Phone | AO8: incentive | AP8: Commission
B9: Mr. Somphone | C9: √ | D9: √ | E9: √ | F9: √ | G9: √ | J9: √ | K9: √ | L9: √ | M9: √ | N9: √ | O9: √ | Q9: √ | R9: √ | S9: √ | T9: √ | U9: √ | V9: √ | X9: √ | Y9: √ | Z9: √ | AA9: √ | AB9: √ | AE9: √ | AF9: √ | AH9: =COUNTA(September[[#This Row],[1]:[ ]]) -> 24 | AP9: =AC5*September[[#This Row],[Total days]] -> 574763.36
B10: Mr. Tusackda | C10: √ | E10: √ | F10: √ | J10: √ | K10: √ | L10: √ | M10: √ | O10: √ | Q10: √ | R10: √ | S10: √ | T10: √ | U10: √ | V10: √ | X10: √ | Y10: √ | Z10: √ | AA10: √ | AB10: √ | AE10: √ | AF10: √ | AH10: =COUNTA(September[[#This Row],[1]:[ ]]) -> 21 | AK10: =SUM(AL10:AP10) -> 6312917.9 | AL10: 5500000 | AM10: =$AI$5*August[[#This Row],[Total days]] -> 260000 | AN10: 50000 | AP10: =September[[#This Row],[Total days]]*AC5 -> 502917.94 | AQ10: =2000000-1646000 -> 354000 | AR10: Advance 25.09.2025
B11: Mr. Vone | C11: √ | D11: √ | E11: √ | F11: √ | G11: √ | J11: √ | K11: √ | L11: √ | M11: √ | N11: √ | O11: √ | Q11: √ | R11: √ | S11: √ | T11: √ | U11: √ | V11: √ | X11: √ | Y11: √ | Z11: √ | AA11: √ | AB11: √ | AC11: √ | AE11: √ | AF11: √ | AH11: =COUNTA(September[[#This Row],[1]:[ ]]) -> 25 | AK11: =SUM(AL11:AP11) -> 6128711.8 | AL11: 5000000 | AM11: =$AI$5*August[[#This Row],[Total days]] -> 480000 | AN11: 50000 | AP11: =AC5*September[[#This Row],[Total days]] -> 598711.83
B12: Mss. Tor | C12: √ | D12: √ | E12: √ | F12: √ | J12: √ | K12: √ | L12: √ | Q12: √ | R12: √ | S12: √ | T12: √ | U12: √ | V12: √ | X12: √ | Y12: √ | Z12: √ | AA12: √ | AB12: √ | AE12: √ | AF12: √ | AH12: =COUNTA(September[[#This Row],[1]:[ ]]) -> 20 | AK12: =SUM(AL12:AP12) -> 5068969.5 | AL12: 4100000 | AM12: =$AI$5*August[[#This Row],[Total days]] -> 440000 | AN12: 50000 | AP12: =AC5*September[[#This Row],[Total days]] -> 478969.47
B13: Ms. Som | C13: √ | D13: √ | E13: √ | F13: √ | G13: √ | J13: √ | K13: √ | L13: √ | N13: √ | Q13: √ | R13: √ | S13: √ | T13: √ | U13: √ | V13: √ | X13: √ | Y13: √ | Z13: √ | AA13: √ | AB13: √ | AE13: √ | AF13: √ | AH13: =COUNTA(September[[#This Row],[1]:[ ]]) -> 22 | AK13: =SUM(AL13:AP13) -> 5276866.4 | AL13: 4200000 | AM13: =$AI$5*August[[#This Row],[Total days]] -> 500000 | AN13: 50000 | AP13: =AC5*September[[#This Row],[Total days]] -> 526866.41 | AQ13: 326000 | AR13: Advance 25.09.2025
B14: Mr. Tay | D14: √ | G14: √ | K14: √ | L14: √ | M14: √ | N14: √ | R14: √ | S14: √ | T14: √ | U14: √ | V14: √ | X14: √ | Y14: √ | Z14: √ | AA14: √ | AB14: √ | AC14: √ | AE14: √ | AF14: √ | AH14: =COUNTA(September[[#This Row],[1]:[ ]]) -> 19 | AK14: =SUM(AL14:AP14) -> 5465021 | AL14: 4500000 | AM14: =$AI$5*August[[#This Row],[Total days]] -> 460000 | AN14: 50000 | AP14: =September[[#This Row],[Total days]]*AC5 -> 455020.99 | AQ14: 1000000 | AR14: Advance 19.09.2025
AH15: =COUNTA(September[[#This Row],[1]:[ ]]) -> 0
B16: =MonthName&" Total" -> September Total | C16: =SUBTOTAL(103,September[1]) -> 5 | D16: =SUBTOTAL(103,September[2]) -> 5 | E16: =SUBTOTAL(103,September[3]) -> 5 | F16: =SUBTOTAL(103,September[4]) -> 5 | G16: =SUBTOTAL(103,September[5]) -> 4 | H16: =SUBTOTAL(103,September[6]) -> 0 | I16: =SUBTOTAL(103,September[7]) -> 0 | J16: =SUBTOTAL(103,September[8]) -> 5 | K16: =SUBTOTAL(103,September[9]) -> 6 | L16: =SUBTOTAL(103,September[10]) -> 6 | M16: =SUBTOTAL(103,September[11]) -> 4 | N16: =SUBTOTAL(103,September[12]) -> 4 | O16: =SUBTOTAL(103,September[13]) -> 3 | P16: =SUBTOTAL(103,September[14]) -> 0 | Q16: =SUBTOTAL(103,September[15]) -> 5 | R16: =SUBTOTAL(103,September[16]) -> 6 | S16: =SUBTOTAL(103,September[17]) -> 6 | T16: =SUBTOTAL(103,September[18]) -> 6 | U16: =SUBTOTAL(103,September[19]) -> 6 | V16: =SUBTOTAL(103,September[20]) -> 6 | W16: =SUBTOTAL(103,September[21]) -> 0 | X16: =SUBTOTAL(103,September[22]) -> 6 | Y16: =SUBTOTAL(103,September[23]) -> 6 | Z16: =SUBTOTAL(103,September[24]) -> 6 | AA16: =SUBTOTAL(103,September[25]) -> 6 | AB16: =SUBTOTAL(103,September[26]) -> 6 | AC16: =SUBTOTAL(103,September[27]) -> 2 | AD16: =SUBTOTAL(103,September[28]) -> 0 | AE16: =SUBTOTAL(103,September[29]) -> 6 | AF16: =SUBTOTAL(109,September[30]) -> 0 | AG16: =SUBTOTAL(109,September[[ ]]) -> 0 | AH16: =SUBTOTAL(109,September[Total days]) -> 131 | AK16: =SUM(AK9:AK14) -> 28252487 | AL16: =SUM(AL9:AL14) -> 23300000 | AM16: =SUM(AM9:AM14) -> 2140000 | AN16: =SUM(AN9:AN14) -> 250000 | AO16: =SUM(AO9:AO14) -> 0 | AP16: =SUM(AP9:AP14) -> 3137250
AK17: =AK10-AQ10 -> 5958917.9
AK18: =12:12 -> 5068969.5
AK19: =AK13-AQ13 -> 4950866.4

Sheet October
C1: Employee absence schedule
C2: October
C4: Absence type key | D4: V | E4: Vacation | H4: A | I4: Annual leave | L4: S | M4: Sick leave | X4: Amount Commission, LAK | AD4: Amount Commission/day | AJ4: Meal/day
AD5: =X5/June[[#Totals],[Working Day]] -> 0 | AJ5: 20000
D6: Dates of absence | AI6: =CalendarYear -> 2026
D7: =TEXT(WEEKDAY(DATE(CalendarYear,10,1),1),"aaa") -> Thu | E7: =TEXT(WEEKDAY(DATE(CalendarYear,10,2),1),"aaa") -> Fri | F7: =TEXT(WEEKDAY(DATE(CalendarYear,10,3),1),"aaa") -> Sat | G7: =TEXT(WEEKDAY(DATE(CalendarYear,10,4),1),"aaa") -> Sun | H7: =TEXT(WEEKDAY(DATE(CalendarYear,10,5),1),"aaa") -> Mon | I7: =TEXT(WEEKDAY(DATE(CalendarYear,10,6),1),"aaa") -> Tue | J7: =TEXT(WEEKDAY(DATE(CalendarYear,10,7),1),"aaa") -> Wed | K7: =TEXT(WEEKDAY(DATE(CalendarYear,10,8),1),"aaa") -> Thu | L7: =TEXT(WEEKDAY(DATE(CalendarYear,10,9),1),"aaa") -> Fri | M7: =TEXT(WEEKDAY(DATE(CalendarYear,10,10),1),"aaa") -> Sat | N7: =TEXT(WEEKDAY(DATE(CalendarYear,10,11),1),"aaa") -> Sun | O7: =TEXT(WEEKDAY(DATE(CalendarYear,10,12),1),"aaa") -> Mon | P7: =TEXT(WEEKDAY(DATE(CalendarYear,10,13),1),"aaa") -> Tue | Q7: =TEXT(WEEKDAY(DATE(CalendarYear,10,14),1),"aaa") -> Wed | R7: =TEXT(WEEKDAY(DATE(CalendarYear,10,15),1),"aaa") -> Thu | S7: =TEXT(WEEKDAY(DATE(CalendarYear,10,16),1),"aaa") -> Fri | T7: =TEXT(WEEKDAY(DATE(CalendarYear,10,17),1),"aaa") -> Sat | U7: =TEXT(WEEKDAY(DATE(CalendarYear,10,18),1),"aaa") -> Sun | V7: =TEXT(WEEKDAY(DATE(CalendarYear,10,19),1),"aaa") -> Mon | W7: =TEXT(WEEKDAY(DATE(CalendarYear,10,20),1),"aaa") -> Tue | X7: =TEXT(WEEKDAY(DATE(CalendarYear,10,21),1),"aaa") -> Wed | Y7: =TEXT(WEEKDAY(DATE(CalendarYear,10,22),1),"aaa") -> Thu | Z7: =TEXT(WEEKDAY(DATE(CalendarYear,10,23),1),"aaa") -> Fri | AA7: =TEXT(WEEKDAY(DATE(CalendarYear,10,24),1),"aaa") -> Sat | AB7: =TEXT(WEEKDAY(DATE(CalendarYear,10,25),1),"aaa") -> Sun | AC7: =TEXT(WEEKDAY(DATE(CalendarYear,10,26),1),"aaa") -> Mon | AD7: =TEXT(WEEKDAY(DATE(CalendarYear,10,27),1),"aaa") -> Tue | AE7: =TEXT(WEEKDAY(DATE(CalendarYear,10,28),1),"aaa") -> Wed | AF7: =TEXT(WEEKDAY(DATE(CalendarYear,10,29),1),"aaa") -> Thu | AG7: =TEXT(WEEKDAY(DATE(CalendarYear,10,30),1),"aaa") -> Fri | AH7: =TEXT(WEEKDAY(DATE(CalendarYear,10,31),1),"aaa") -> Sat
B8: No | C8: Employee name | D8: 1 | E8: 2 | F8: 3 | G8: 4 | H8: 5 | I8: 6 | J8: 7 | K8: 8 | L8: 9 | M8: 10 | N8: 11 | O8: 12 | P8: 13 | Q8: 14 | R8: 15 | S8: 16 | T8: 17 | U8: 18 | V8: 19 | W8: 20 | X8: 21 | Y8: 22 | Z8: 23 | AA8: 24 | AB8: 25 | AC8: 26 | AD8: 27 | AE8: 28 | AF8: 29 | AG8: 30 | AH8: 31 | AI8: Total days | AL8: Amount in month | AM8: Salary | AN8: Meal | AO8: Phone | AP8: incentive | AQ8: Commission
B9: 1 | C9: Mr. SOMPHONE XAYASA | D9: √ | E9: √ | F9: √ | G9: √ | I9: √ | J9: √ | K9: √ | L9: √ | M9: √ | N9: √ | P9: √ | Q9: √ | R9: √ | S9: √ | T9: √ | U9: √ | W9: √ | X9: √ | Y9: √ | Z9: √ | AA9: √ | AB9: √ | AL9: =SUM(AM9:AQ9) -> 10000000 | AM9: 10000000 | AN9: =AJ5*October[[#This Row],[Total days]] -> 0
B10: 2 | C10: MISS. SOUKSAKHONE CHONPATHOUMA | D10: √ | E10: √ | F10: √ | G10: √ | I10: √ | J10: √ | K10: √ | L10: √ | M10: √ | N10: √ | P10: √ | Q10: √ | R10: √ | S10: √ | T10: √ | U10: √ | W10: √ | X10: √ | Y10: √ | Z10: √ | AA10: √ | AB10: √ | AL10: =SUM(AM10:AQ10) -> 5000000 | AM10: 5000000 | AN10: =$AJ$5*October[[#This Row],[Total days]] -> 0
B11: 3 | C11: Mr. KHAMLAR CHITTAMANY | D11: √ | E11: √ | F11: √ | G11: √ | I11: √ | J11: √ | K11: √ | L11: √ | M11: √ | N11: √ | P11: √ | Q11: √ | R11: √ | S11: √ | T11: √ | U11: √ | W11: √ | X11: √ | Y11: √ | Z11: √ | AA11: √ | AB11: √ | AL11: =SUM(AM11:AQ11) -> 2000000 | AM11: 2000000 | AN11: =$AJ$5*October[[#This Row],[Total days]] -> 0
B12: 4 | C12: Mr. SIVONE MANACHACK | D12: √ | E12: √ | F12: √ | G12: √ | I12: √ | J12: √ | K12: √ | L12: √ | M12: √ | N12: √ | P12: √ | Q12: √ | R12: √ | S12: √ | T12: √ | U12: √ | W12: √ | X12: √ | Y12: √ | Z12: √ | AA12: √ | AB12: √ | AI12: =COUNTA(October[[#This Row],[1]:[31]]) -> 22 | AL12: =SUM(AM12:AQ12) -> 5490000 | AM12: 5000000 | AN12: =$AJ$5*October[[#This Row],[Total days]] -> 440000 | AO12: 50000
B13: 5 | C13: Mr. VONGSAVATH VONGPASEUTH | D13: √ | E13: √ | F13: √ | G13: √ | I13: √ | J13: √ | K13: √ | L13: √ | M13: √ | N13: √ | P13: √ | Q13: √ | R13: √ | S13: √ | T13: √ | U13: √ | W13: √ | X13: √ | Y13: √ | Z13: √ | AA13: √ | AB13: √ | AL13: =SUM(AM13:AQ13) -> 0 | AN13: =$AJ$5*October[[#This Row],[Total days]] -> 0
B14: 6 | C14: Mss. CHAMPA LUANGAPHAI | D14: √ | E14: √ | F14: √ | G14: √ | I14: √ | J14: √ | K14: √ | L14: √ | M14: √ | N14: √ | P14: √ | Q14: √ | R14: √ | S14: √ | T14: √ | U14: √ | W14: √ | X14: √ | Y14: √ | Z14: √ | AA14: √ | AB14: √ | AL14: =SUM(AM14:AQ14) -> 0 | AN14: =$AJ$5*October[[#This Row],[Total days]] -> 0
B15: 7 | C15: Mr. TUSACKDA XAYASA | D15: √ | E15: √ | F15: √ | G15: √ | I15: √ | J15: √ | K15: √ | L15: √ | M15: √ | N15: √ | P15: √ | Q15: √ | R15: √ | S15: √ | T15: √ | U15: √ | W15: √ | X15: √ | Y15: √ | Z15: √ | AA15: √ | AB15: √ | AI15: =COUNTA(October[[#This Row],[1]:[31]]) -> 22 | AL15: =SUM(AM15:AQ15) -> 5990000 | AM15: 5500000 | AN15: =$AJ$5*October[[#This Row],[Total days]] -> 440000 | AO15: 50000
B16: 8 | C16: Mss. TOR | D16: √ | E16: √ | F16: √ | G16: √ | I16: √ | J16: √ | K16: √ | L16: √ | M16: √ | N16: √ | P16: √ | Q16: √ | R16: √ | S16: √ | T16: √ | U16: √ | W16: √ | X16: √ | Y16: √ | Z16: √ | AA16: √ | AB16: √ | AL16: =SUM(AM16:AQ16) -> 4000000 | AM16: 4000000 | AN16: =$AJ$5*October[[#This Row],[Total days]] -> 0
B17: 9 | C17: MS. OULAYVANH NGAVINAM | D17: √ | E17: √ | F17: √ | G17: √ | I17: √ | J17: √ | K17: √ | L17: √ | M17: √ | N17: √ | P17: √ | Q17: √ | R17: √ | S17: √ | T17: √ | U17: √ | W17: √ | X17: √ | Y17: √ | Z17: √ | AA17: √ | AB17: √ | AL17: =SUM(AM17:AQ17) -> 7500000 | AM17: 7500000 | AN17: =$AJ$5*October[[#This Row],[Total days]] -> 0
B18: 10 | AI18: =COUNTA(October[[#This Row],[1]:[31]]) -> 0 | AL18: =SUM(AM18:AQ18) -> 0 | AN18: =$AJ$5*October[[#This Row],[Total days]] -> 0
B19: 11 | AI19: =COUNTA(October[[#This Row],[1]:[31]]) -> 0 | AL19: =SUM(AM19:AQ19) -> 0 | AN19: =$AJ$5*October[[#This Row],[Total days]] -> 0
B20: 12 | AI20: =COUNTA(October[[#This Row],[1]:[31]]) -> 0 | AL20: =SUM(AM20:AQ20) -> 0 | AN20: =$AJ$5*October[[#This Row],[Total days]] -> 0
B21: 13 | AI21: =COUNTA(October[[#This Row],[1]:[31]]) -> 0 | AL21: =SUM(AM21:AQ21) -> 0 | AN21: =$AJ$5*October[[#This Row],[Total days]] -> 0
C22: =MonthName&" Total" -> October Total | D22: =SUBTOTAL(103,October[1]) -> 9 | E22: =SUBTOTAL(103,October[2]) -> 9 | F22: =SUBTOTAL(103,October[3]) -> 9 | G22: =SUBTOTAL(103,October[4]) -> 9 | H22: =SUBTOTAL(103,October[5]) -> 0 | I22: =SUBTOTAL(103,October[6]) -> 9 | J22: =SUBTOTAL(103,October[7]) -> 9 | K22: =SUBTOTAL(103,October[8]) -> 9 | L22: =SUBTOTAL(103,October[9]) -> 9 | M22: =SUBTOTAL(103,October[10]) -> 9 | N22: =SUBTOTAL(103,October[11]) -> 9 | O22: =SUBTOTAL(103,October[12]) -> 0 | P22: =SUBTOTAL(103,October[13]) -> 9 | Q22: =SUBTOTAL(103,October[14]) -> 9 | R22: =SUBTOTAL(103,October[15]) -> 9 | S22: =SUBTOTAL(103,October[16]) -> 9 | T22: =SUBTOTAL(103,October[17]) -> 9 | U22: =SUBTOTAL(103,October[18]) -> 9 | V22: =SUBTOTAL(103,October[19]) -> 0 | W22: =SUBTOTAL(103,October[20]) -> 9 | X22: =SUBTOTAL(103,October[21]) -> 9 | Y22: =SUBTOTAL(103,October[22]) -> 9 | Z22: =SUBTOTAL(103,October[23]) -> 9 | AA22: =SUBTOTAL(103,October[24]) -> 9 | AB22: =SUBTOTAL(103,October[25]) -> 9 | AC22: =SUBTOTAL(103,October[26]) -> 0 | AD22: =SUBTOTAL(103,October[27]) -> 0 | AE22: =SUBTOTAL(103,October[28]) -> 0 | AF22: =SUBTOTAL(103,October[29]) -> 0 | AG22: =SUBTOTAL(109,October[30]) -> 0 | AH22: =SUBTOTAL(109,October[31]) -> 0 | AI22: =SUBTOTAL(109,October[Total days]) -> 44 | AL22: =SUM(AL9:AL21) -> 39980000 | AM22: =SUM(AM9:AM21) -> 39000000 | AN22: =SUM(AN9:AN21) -> 880000 | AO22: =SUM(AO9:AO21) -> 100000 | AP22: =SUM(AP9:AP21) -> 0 | AQ22: =SUM(AQ9:AQ21) -> 0

Sheet November
D1: Employee absence schedule
D2: November
C4: Absence type key | D4: V | E4: Vacation | H4: A | I4: Annual leave | L4: S | M4: Sick leave | X4: Amount Commission, LAK | AD4: Amount Commission/day | AJ4: Meal/day
U5: =4500000/AI9 -> 214285.71 | AD5: =X5/June[[#Totals],[Working Day]] -> 0 | AJ5: 20000
E6: Dates of absence | AJ6: =CalendarYear -> 2026
D7: =TEXT(WEEKDAY(DATE(CalendarYear,11,1),1),"aaa") -> Sun | E7: =TEXT(WEEKDAY(DATE(CalendarYear,11,2),1),"aaa") -> Mon | F7: =TEXT(WEEKDAY(DATE(CalendarYear,11,3),1),"aaa") -> Tue | G7: =TEXT(WEEKDAY(DATE(CalendarYear,11,4),1),"aaa") -> Wed | H7: =TEXT(WEEKDAY(DATE(CalendarYear,11,5),1),"aaa") -> Thu | I7: =TEXT(WEEKDAY(DATE(CalendarYear,11,6),1),"aaa") -> Fri | J7: =TEXT(WEEKDAY(DATE(CalendarYear,11,7),1),"aaa") -> Sat | K7: =TEXT(WEEKDAY(DATE(CalendarYear,11,8),1),"aaa") -> Sun | L7: =TEXT(WEEKDAY(DATE(CalendarYear,11,9),1),"aaa") -> Mon | M7: =TEXT(WEEKDAY(DATE(CalendarYear,11,10),1),"aaa") -> Tue | N7: =TEXT(WEEKDAY(DATE(CalendarYear,11,11),1),"aaa") -> Wed | O7: =TEXT(WEEKDAY(DATE(CalendarYear,11,12),1),"aaa") -> Thu | P7: =TEXT(WEEKDAY(DATE(CalendarYear,11,13),1),"aaa") -> Fri | Q7: =TEXT(WEEKDAY(DATE(CalendarYear,11,14),1),"aaa") -> Sat | R7: =TEXT(WEEKDAY(DATE(CalendarYear,11,15),1),"aaa") -> Sun | S7: =TEXT(WEEKDAY(DATE(CalendarYear,11,16),1),"aaa") -> Mon | T7: =TEXT(WEEKDAY(DATE(CalendarYear,11,17),1),"aaa") -> Tue | U7: =TEXT(WEEKDAY(DATE(CalendarYear,11,18),1),"aaa") -> Wed | V7: =TEXT(WEEKDAY(DATE(CalendarYear,11,19),1),"aaa") -> Thu | W7: =TEXT(WEEKDAY(DATE(CalendarYear,11,20),1),"aaa") -> Fri | X7: =TEXT(WEEKDAY(DATE(CalendarYear,11,21),1),"aaa") -> Sat | Y7: =TEXT(WEEKDAY(DATE(CalendarYear,11,22),1),"aaa") -> Sun | Z7: =TEXT(WEEKDAY(DATE(CalendarYear,11,23),1),"aaa") -> Mon | AA7: =TEXT(WEEKDAY(DATE(CalendarYear,11,24),1),"aaa") -> Tue | AB7: =TEXT(WEEKDAY(DATE(CalendarYear,11,25),1),"aaa") -> Wed | AC7: =TEXT(WEEKDAY(DATE(CalendarYear,11,26),1),"aaa") -> Thu | AD7: =TEXT(WEEKDAY(DATE(CalendarYear,11,27),1),"aaa") -> Fri | AE7: =TEXT(WEEKDAY(DATE(CalendarYear,11,28),1),"aaa") -> Sat | AF7: =TEXT(WEEKDAY(DATE(CalendarYear,11,29),1),"aaa") -> Sun | AG7: =TEXT(WEEKDAY(DATE(CalendarYear,11,30),1),"aaa") -> Mon
B8: No | C8: Employee name | D8: 1 | E8: 2 | F8: 3 | G8: 4 | H8: 5 | I8: 6 | J8: 7 | K8: 8 | L8: 9 | M8: 10 | N8: 11 | O8: 12 | P8: 13 | Q8: 14 | R8: 15 | S8: 16 | T8: 17 | U8: 18 | V8: 19 | W8: 20 | X8: 21 | Y8: 22 | Z8: 23 | AA8: 24 | AB8: 25 | AC8: 26 | AD8: 27 | AE8: 28 | AF8: 29 | AG8: 30 | AI8: Total days | AL8: Amount in month | AM8: Salary | AN8: Real working day | AO8: Meal | AP8: Phone | AQ8: OT | AR8: incentive | AS8: Commission
B9: 1 | C9: Mr. SOMPHONE XAYASA | F9: √ | G9: √ | H9: √ | I9: √ | J9: √ | K9: √ | L9: √ | M9: √ | N9: √ | O9: √ | P9: √ | Q9: √ | R9: √ | T9: √ | U9: √ | V9: √ | W9: √ | X9: √ | Y9: √ | AA9: √ | AB9: √ | AI9: =COUNTA(November[[#This Row],[1]:[ ]]) -> 21 | AL9: =SUM(AM9:AU9) -> 10000000 | AM9: 10000000 | AT9: CEO
B10: 2 | AI10: =COUNTA(November[[#This Row],[1]:[ ]]) -> 0 | AL10: =SUM(AM10:AU10) -> 0 | AM10: 0 | AO10: =$AJ$5*October[[#This Row],[Total days]] -> 0 | AT10: CFO
B11: 2 | C11: MISS. SOUKSAKHONE CHONPATHOUMA | F11: √ | G11: √ | H11: √ | I11: √ | J11: √ | K11: √ | M11: √ | N11: √ | O11: √ | P11: √ | Q11: √ | R11: √ | T11: √ | U11: √ | V11: √ | W11: √ | X11: √ | Y11: √ | AA11: √ | AB11: √ | AI11: =COUNTA(November[[#This Row],[1]:[ ]]) -> 20 | AL11: =SUM(AM11:AU11) -> 5000000 | AM11: 5000000 | AO11: =$AJ$5*October[[#This Row],[Total days]] -> 0 | AT11: CHR
B12: 3 | C12: Mr. KHAMLAR CHITTAMANY | F12: √ | G12: √ | H12: √ | I12: √ | J12: √ | M12: √ | N12: √ | O12: √ | P12: √ | Q12: √ | T12: √ | U12: √ | V12: √ | W12: √ | X12: √ | AA12: √ | AB12: √ | AI12: =COUNTA(November[[#This Row],[1]:[ ]]) -> 17 | AL12: =SUM(AM12:AU12) -> 2000000 | AM12: 2000000 | AT12: CONS
B13: 4 | C13: MS. OULAYVANH NGAVINAM | F13: √ | G13: √ | H13: √ | I13: √ | J13: √ | M13: √ | N13: √ | O13: √ | P13: √ | Q13: √ | T13: √ | U13: √ | V13: √ | W13: √ | X13: √ | AA13: √ | AB13: √ | AI13: =COUNTA(November[[#This Row],[1]:[ ]]) -> 17 | AL13: =SUM(AM13:AU13) -> 7500000 | AM13: 7500000 | AO13: =$AJ$5*October[[#This Row],[Total days]] -> 0 | AT13: ASS
B14: 5 | C14: MS. VILAYPHONE VONGPHACKDE | F14: √ | G14: √ | H14: √ | I14: √ | J14: √ | M14: √ | N14: √ | O14: √ | P14: √ | Q14: √ | T14: √ | U14: √ | V14: √ | W14: √ | X14: √ | AI14: =COUNTA(November[[#This Row],[1]:[ ]]) -> 15 | AL14: =SUM(AN14:AS14) -> 3418181.8 | AM14: 4500000 | AN14: =(AM14/22)*November[[#This Row],[Total days]] -> 3068181.8 | AO14: =AJ5*November[[#This Row],[Total days]] -> 300000 | AP14: 50000 | AT14: ACC
B15: 6 | C15: Mr. SIVONE MANACHACK (Vone) | F15: √ | G15: √ | H15: √ | I15: √ | J15: √ | K15: √ | L15: √ | M15: √ | N15: √ | O15: √ | P15: √ | Q15: √ | R15: √ | U15: √ | V15: √ | W15: √ | X15: √ | Y15: √ | AA15: √ | AB15: √ | AG15: √ | AI15: =COUNTA(November[[#This Row],[1]:[ ]]) -> 21 | AL15: =SUM(AM15:AS15) -> 6026189.9 | AM15: 5125000 | AO15: =AJ5*November[[#This Row],[Total days]] -> 420000 | AP15: 50000 | AQ15: =AA30 -> 431189.9 | AT15: TECH
B16: 7 | C16: Mr. SOMPHONE KEOPHILAVANH (Olay) | K16: √ | L16: √ | M16: √ | N16: √ | O16: √ | P16: √ | Q16: √ | R16: √ | T16: √ | U16: √ | V16: √ | W16: √ | X16: √ | Y16: √ | AA16: √ | AB16: √ | AG16: √ | AI16: =COUNTA(November[[#This Row],[1]:[ ]]) -> 17 | AL16: =SUM(AN16:AS16) -> 4021663 | AM16: 4250000 | AN16: =(AM16/22)*November[[#This Row],[Total days]] -> 3284090.9 | AO16: =AJ5*November[[#This Row],[Total days]] -> 340000 | AP16: 40000 | AQ16: =AA31 -> 357572.12 | AT16: TECH
B17: 8 | C17: Mr. TUSACKDA XAYASA (Tu) | F17: √ | G17: √ | H17: √ | I17: √ | J17: √ | K17: √ | L17: √ | M17: √ | N17: √ | O17: √ | P17: √ | Q17: √ | R17: √ | T17: √ | U17: √ | V17: √ | W17: √ | Y17: √ | AA17: √ | AB17: √ | AG17: √ | AI17: =COUNTA(November[[#This Row],[1]:[ ]]) -> 21 | AL17: =SUM(AM17:AS17) -> 6247644.2 | AM17: 5500000 | AO17: =AJ5*November[[#This Row],[Total days]] -> 420000 | AP17: 50000 | AQ17: =AA32 -> 277644.23 | AT17: TECH
B18: 9 | C18: Mr. THAVONE CHANTHY (Add) | J18: √ | K18: √ | L18: √ | M18: √ | N18: √ | O18: √ | P18: √ | Q18: √ | T18: √ | U18: √ | V18: √ | W18: √ | X18: √ | AA18: √ | AB18: √ | AI18: =COUNTA(November[[#This Row],[1]:[ ]]) -> 15 | AL18: =SUM(AN18:AS18) -> 4277500 | AM18: 4500000 | AN18: =(AM18/22)*November[[#This Row],[Total days]] -> 3068181.8 | AO18: =AJ5*November[[#This Row],[Total days]] -> 300000 | AP18: 40000 | AQ18: =AA33 -> 869318.18 | AT18: DRIVER
B19: 10 | C19: Mr.KHANKHAM MARAVONG (Kol) | J19: √ | K19: √ | M19: √ | N19: √ | O19: √ | P19: √ | Q19: √ | T19: √ | U19: √ | V19: √ | W19: √ | X19: √ | AA19: √ | AB19: √ | AI19: =COUNTA(November[[#This Row],[1]:[ ]]) -> 14 | AL19: =SUM(AN19:AS19) -> 3605511.4 | AM19: 4500000 | AN19: =(AM19/22)*November[[#This Row],[Total days]] -> 2863636.4 | AO19: =AJ5*November[[#This Row],[Total days]] -> 280000 | AP19: 40000 | AQ19: =AA34 -> 421875 | AT19: DRIVER
B20: 11 | C20: Mr. SUKAN MUENXAYYAPHOM (Yao) | N20: √ | O20: √ | P20: √ | Q20: √ | T20: √ | U20: √ | V20: √ | W20: √ | X20: √ | AA20: √ | AB20: √ | AI20: =COUNTA(November[[#This Row],[1]:[ ]]) -> 11 | AL20: =SUM(AN20:AS20) -> 2510000 | AM20: 4500000 | AN20: =(AM20/22)*November[[#This Row],[Total days]] -> 2250000 | AO20: =AJ5*November[[#This Row],[Total days]] -> 220000 | AP20: 40000 | AT20: DRIVER
B21: 12 | C21: Mr. KITTIPHONG SEESOULASACK (beer) | K21: √ | M21: √ | N21: √ | O21: √ | P21: √ | Q21: √ | T21: √ | U21: √ | V21: √ | W21: √ | X21: √ | AA21: √ | AB21: √ | AI21: =COUNTA(November[[#This Row],[1]:[ ]]) -> 13 | AL21: =SUM(AN21:AS21) -> 3209801.1 | AM21: 4250000 | AN21: =(AM21/22)*November[[#This Row],[Total days]] -> 2511363.6 | AO21: =AJ5*November[[#This Row],[Total days]] -> 260000 | AP21: 40000 | AQ21: =AA35 -> 398437.5 | AT21: Merchandiser
B22: 13 | C22: Mr. PHOUTTHASONE SILIPANYA (Too) | K22: √ | M22: √ | N22: √ | O22: √ | P22: √ | Q22: √ | T22: √ | U22: √ | V22: √ | W22: √ | X22: √ | AA22: √ | AB22: √ | AI22: =COUNTA(November[[#This Row],[1]:[ ]]) -> 13 | AL22: =SUM(AN22:AS22) -> 3209801.1 | AM22: 4250000 | AN22: =(AM22/22)*November[[#This Row],[Total days]] -> 2511363.6 | AO22: =AJ5*November[[#This Row],[Total days]] -> 260000 | AP22: 40000 | AQ22: =AA36 -> 398437.5 | AT22: Merchandiser
B23: 14 | C23: Mr. SOUKSAVANH PHANNIVONGSOR (Thop) | J23: √ | K23: √ | M23: √ | N23: √ | O23: √ | P23: √ | Q23: √ | T23: √ | U23: √ | V23: √ | W23: √ | X23: √ | AA23: √ | AB23: √ | AI23: =COUNTA(November[[#This Row],[1]:[ ]]) -> 14 | AL23: =SUM(AN23:AS23) -> 3422983 | AM23: 4250000 | AN23: =(AM23/22)*November[[#This Row],[Total days]] -> 2704545.5 | AO23: =AJ5*November[[#This Row],[Total days]] -> 280000 | AP23: 40000 | AQ23: =AA37 -> 398437.5 | AT23: Merchandiser
B24: 15 | C24: Mss. SIRIPHUN KHOUNHAVONG (Tor) | F24: √ | G24: √ | H24: √ | I24: √ | J24: √ | M24: √ | N24: √ | O24: √ | P24: √ | Q24: √ | T24: √ | U24: √ | V24: √ | W24: √ | X24: √ | AA24: √ | AI24: =COUNTA(November[[#This Row],[1]:[ ]]) -> 16 | AL24: =SUM(AM24:AU24) -> 4000000 | AM24: 4000000 | AT24: HK
C25: =MonthName&" Total" -> Total | D25: =SUBTOTAL(103,November[1]) -> 0 | E25: =SUBTOTAL(103,November[2]) -> 0 | F25: =SUBTOTAL(103,November[3]) -> 8 | G25: =SUBTOTAL(103,November[4]) -> 8 | H25: =SUBTOTAL(103,November[5]) -> 8 | I25: =SUBTOTAL(103,November[6]) -> 8 | J25: =SUBTOTAL(103,November[7]) -> 11 | K25: =SUBTOTAL(103,November[8]) -> 10 | L25: =SUBTOTAL(103,November[9]) -> 5 | M25: =SUBTOTAL(103,November[10]) -> 14 | N25: =SUBTOTAL(103,November[11]) -> 15 | O25: =SUBTOTAL(103,November[12]) -> 15 | P25: =SUBTOTAL(103,November[13]) -> 15 | Q25: =SUBTOTAL(103,November[14]) -> 15 | R25: =SUBTOTAL(103,November[15]) -> 5 | S25: =SUBTOTAL(103,November[16]) -> 0 | T25: =SUBTOTAL(103,November[17]) -> 14 | U25: =SUBTOTAL(103,November[18]) -> 15 | V25: =SUBTOTAL(103,November[19]) -> 15 | W25: =SUBTOTAL(103,November[20]) -> 15 | X25: =SUBTOTAL(103,November[21]) -> 14 | Y25: =SUBTOTAL(103,November[22]) -> 5 | Z25: =SUBTOTAL(103,November[23]) -> 0 | AA25: =SUBTOTAL(103,November[24]) -> 14 | AB25: =SUBTOTAL(103,November[25]) -> 13 | AC25: =SUBTOTAL(103,November[26]) -> 0 | AD25: =SUBTOTAL(103,November[27]) -> 0 | AE25: =SUBTOTAL(103,November[28]) -> 0 | AF25: =SUBTOTAL(103,November[29]) -> 0 | AG25: =SUBTOTAL(109,November[30]) -> 0 | AH25: =SUBTOTAL(109,November[[ ]]) -> 0 | AI25: =SUBTOTAL(109,November[Total days]) -> 245 | AL25: =SUM(AL9:AL24) -> 68449276 | AM25: =SUM(AM9:AM24) -> 74125000 | AO25: =SUM(AO9:AO24) -> 3080000 | AP25: =SUM(AP9:AP24) -> 430000 | AR25: =SUM(AR9:AR24) -> 0 | AS25: =SUM(AS9:AS24) -> 0
C28: List name of OT | D28: Normal OT day | O28: OT holiday (Sunday) | AA28: Total | AG28: Notation
B29: 1 | C29: Mr. SOMPHONE XAYASA | I29: =AM31*D29 -> 0 | AA29: =I29+U29 -> 0
B30: 1 | C30: Mr. SIVONE MANACHACK (Vone) | I30: =AM32*D30 -> 0 | O30: 7 | U30: =AO32*O30 -> 431189.9 | AA30: =I30+U30 -> 431189.9 | AL30: OT 26ວັນ | AM30: ເສົາ | AO30: ອາທິດ
B31: 2 | C31: Mr. SOMPHONE KEOPHILAVANH (Olay) | I31: =AM33*D31 -> 0 | O31: 7 | U31: =AO33*O31 -> 357572.12 | AA31: =I31+U31 -> 357572.12 | AL31: 5500000 | AM31: =(((AL31/26)/8)*150)/100 -> 39663.462 | AO31: =(((AL31/26)/8)*250%)/100% -> 66105.769
B32: 3 | C32: Mr. TUSACKDA XAYASA (Tu) | I32: =AM31*D32 -> 0 | O32: 7 | U32: =AM31*O32 -> 277644.23 | AA32: =I32+U32 -> 277644.23 | AL32: 5125000 | AM32: =(((AL32/26)/8)*150)/100 -> 36959.135 | AO32: =(((AL32/26)/8)*250%)/100% -> 61598.558
B33: 4 | C33: Mr. THAVONE CHANTHY (Add) | D33: 11 | I33: =AM37*D33 -> 421875 | O33: 7 | U33: =AO37*O33 -> 447443.18 | AA33: =I33+U33 -> 869318.18 | AL33: 4250000 | AM33: =(((AL33/26)/8)*150)/100 -> 30649.038 | AO33: =(((AL33/26)/8)*250%)/100% -> 51081.731
B34: 5 | C34: Mr.KHANKHAM MARAVONG (Kol) | D34: 11 | I34: =AM37*D34 -> 421875 | U34: =AO37*O34 -> 0 | AA34: =I34+U34 -> 421875
B35: 6 | C35: Mr. KITTIPHONG SEESOULASACK (beer) | D35: 11 | I35: =AM36*D35 -> 398437.5 | U35: =AO36*O35 -> 0 | AA35: =I35+U35 -> 398437.5 | AL35: OT 22ວັນ | AM35: ເສົາ | AO35: ອາທິດ
B36: 7 | C36: Mr. PHOUTTHASONE SILIPANYA (Too) | D36: 11 | I36: =AM36*D36 -> 398437.5 | U36: =AO36*O36 -> 0 | AA36: =I36+U36 -> 398437.5 | AL36: 4250000 | AM36: =(((AL36/22)/8)*150)/100 -> 36221.591 | AO36: =(((AL36/22)/8)*250%)/100% -> 60369.318
B37: 8 | C37: Mr. SOUKSAVANH PHANNIVONGSOR (Thop) | D37: 11 | I37: =AM36*D37 -> 398437.5 | U37: =AO36*O37 -> 0 | AA37: =I37+U37 -> 398437.5 | AL37: 4500000 | AM37: =(((AL37/22)/8)*150%)/100% -> 38352.273 | AO37: =(((AL37/22)/8)*250%)/100% -> 63920.455

Sheet December
B1: Employee absence schedule
B2: December
B4: Absence type key | C4: V | D4: Vacation | G4: A | H4: Annual leave | K4: S | L4: Sick leave | W4: Amount Commission, LAK | AC4: Amount Commission/day | AI4: Meal/day
AC5: =W5/June[[#Totals],[Working Day]] -> 0 | AI5: 20000
C6: Dates of absence | AH6: =CalendarYear -> 2026
C7: =TEXT(WEEKDAY(DATE(CalendarYear,12,1),1),"aaa") -> Tue | D7: =TEXT(WEEKDAY(DATE(CalendarYear,12,2),1),"aaa") -> Wed | E7: =TEXT(WEEKDAY(DATE(CalendarYear,12,3),1),"aaa") -> Thu | F7: =TEXT(WEEKDAY(DATE(CalendarYear,12,4),1),"aaa") -> Fri | G7: =TEXT(WEEKDAY(DATE(CalendarYear,12,5),1),"aaa") -> Sat | H7: =TEXT(WEEKDAY(DATE(CalendarYear,12,6),1),"aaa") -> Sun | I7: =TEXT(WEEKDAY(DATE(CalendarYear,12,7),1),"aaa") -> Mon | J7: =TEXT(WEEKDAY(DATE(CalendarYear,12,8),1),"aaa") -> Tue | K7: =TEXT(WEEKDAY(DATE(CalendarYear,12,9),1),"aaa") -> Wed | L7: =TEXT(WEEKDAY(DATE(CalendarYear,12,10),1),"aaa") -> Thu | M7: =TEXT(WEEKDAY(DATE(CalendarYear,12,11),1),"aaa") -> Fri | N7: =TEXT(WEEKDAY(DATE(CalendarYear,12,12),1),"aaa") -> Sat | O7: =TEXT(WEEKDAY(DATE(CalendarYear,12,13),1),"aaa") -> Sun | P7: =TEXT(WEEKDAY(DATE(CalendarYear,12,14),1),"aaa") -> Mon | Q7: =TEXT(WEEKDAY(DATE(CalendarYear,12,15),1),"aaa") -> Tue | R7: =TEXT(WEEKDAY(DATE(CalendarYear,12,16),1),"aaa") -> Wed | S7: =TEXT(WEEKDAY(DATE(CalendarYear,12,17),1),"aaa") -> Thu | T7: =TEXT(WEEKDAY(DATE(CalendarYear,12,18),1),"aaa") -> Fri | U7: =TEXT(WEEKDAY(DATE(CalendarYear,12,19),1),"aaa") -> Sat | V7: =TEXT(WEEKDAY(DATE(CalendarYear,12,20),1),"aaa") -> Sun | W7: =TEXT(WEEKDAY(DATE(CalendarYear,12,21),1),"aaa") -> Mon | X7: =TEXT(WEEKDAY(DATE(CalendarYear,12,22),1),"aaa") -> Tue | Y7: =TEXT(WEEKDAY(DATE(CalendarYear,12,23),1),"aaa") -> Wed | Z7: =TEXT(WEEKDAY(DATE(CalendarYear,12,24),1),"aaa") -> Thu | AA7: =TEXT(WEEKDAY(DATE(CalendarYear,12,25),1),"aaa") -> Fri | AB7: =TEXT(WEEKDAY(DATE(CalendarYear,12,26),1),"aaa") -> Sat | AC7: =TEXT(WEEKDAY(DATE(CalendarYear,12,27),1),"aaa") -> Sun | AD7: =TEXT(WEEKDAY(DATE(CalendarYear,12,28),1),"aaa") -> Mon | AE7: =TEXT(WEEKDAY(DATE(CalendarYear,12,29),1),"aaa") -> Tue | AF7: =TEXT(WEEKDAY(DATE(CalendarYear,12,30),1),"aaa") -> Wed | AG7: =TEXT(WEEKDAY(DATE(CalendarYear,12,31),1),"aaa") -> Thu
B8: Employee name | C8: 1 | D8: 2 | E8: 3 | F8: 4 | G8: 5 | H8: 6 | I8: 7 | J8: 8 | K8: 9 | L8: 10 | M8: 11 | N8: 12 | O8: 13 | P8: 14 | Q8: 15 | R8: 16 | S8: 17 | T8: 18 | U8: 19 | V8: 20 | W8: 21 | X8: 22 | Y8: 23 | Z8: 24 | AA8: 25 | AB8: 26 | AC8: 27 | AD8: 28 | AE8: 29 | AF8: 30 | AG8: 31 | AH8: Total days | AK8: Amount in month | AL8: Salary | AM8: Meal | AN8: Phone | AO8: incentive | AP8: Commission
B9: Harsimran Brar | AH9: =COUNTA(December[[#This Row],[1]:[31]]) -> 0 | AP9: =$AC$5*June[[#This Row],[Working Day]] -> 0
B10: Jordan Mitchell | AH10: =COUNTA(December[[#This Row],[1]:[31]]) -> 0 | AK10: =SUM(AL10:AP10) -> 5310000 | AL10: 4500000 | AM10: =$AI$5*August[[#This Row],[Total days]] -> 260000 | AN10: 50000 | AO10: 500000 | AP10: =$AC$5*June[[#This Row],[Working Day]] -> 0
B11: Asaf Karten | AH11: =COUNTA(December[[#This Row],[1]:[31]]) -> 0 | AK11: =SUM(AL11:AP11) -> 6530000 | AL11: 5500000 | AM11: =$AI$5*August[[#This Row],[Total days]] -> 480000 | AN11: 50000 | AO11: 500000 | AP11: =$AC$5*June[[#This Row],[Working Day]] -> 0
B12: Vanja Jovanovic | AH12: =COUNTA(December[[#This Row],[1]:[31]]) -> 0 | AK12: =SUM(AL12:AP12) -> 4990000 | AL12: 4000000 | AM12: =$AI$5*August[[#This Row],[Total days]] -> 440000 | AN12: 50000 | AO12: 500000 | AP12: =$AC$5*June[[#This Row],[Working Day]] -> 0
B13: Madison Butler | AH13: =COUNTA(December[[#This Row],[1]:[31]]) -> 0 | AK13: =SUM(AL13:AP13) -> 6050000 | AL13: 5000000 | AM13: =$AI$5*August[[#This Row],[Total days]] -> 500000 | AN13: 50000 | AO13: 500000 | AP13: =$AC$5*June[[#This Row],[Working Day]] -> 0
B14: =MonthName&" Total" -> December Total | C14: =SUBTOTAL(103,December[1]) -> 0 | D14: =SUBTOTAL(103,December[2]) -> 0 | E14: =SUBTOTAL(103,December[3]) -> 0 | F14: =SUBTOTAL(103,December[4]) -> 0 | G14: =SUBTOTAL(103,December[5]) -> 0 | H14: =SUBTOTAL(103,December[6]) -> 0 | I14: =SUBTOTAL(103,December[7]) -> 0 | J14: =SUBTOTAL(103,December[8]) -> 0 | K14: =SUBTOTAL(103,December[9]) -> 0 | L14: =SUBTOTAL(103,December[10]) -> 0 | M14: =SUBTOTAL(103,December[11]) -> 0 | N14: =SUBTOTAL(103,December[12]) -> 0 | O14: =SUBTOTAL(103,December[13]) -> 0 | P14: =SUBTOTAL(103,December[14]) -> 0 | Q14: =SUBTOTAL(103,December[15]) -> 0 | R14: =SUBTOTAL(103,December[16]) -> 0 | S14: =SUBTOTAL(103,December[17]) -> 0 | T14: =SUBTOTAL(103,December[18]) -> 0 | U14: =SUBTOTAL(103,December[19]) -> 0 | V14: =SUBTOTAL(103,December[20]) -> 0 | W14: =SUBTOTAL(103,December[21]) -> 0 | X14: =SUBTOTAL(103,December[22]) -> 0 | Y14: =SUBTOTAL(103,December[23]) -> 0 | Z14: =SUBTOTAL(103,December[24]) -> 0 | AA14: =SUBTOTAL(103,December[25]) -> 0 | AB14: =SUBTOTAL(103,December[26]) -> 0 | AC14: =SUBTOTAL(103,December[27]) -> 0 | AD14: =SUBTOTAL(103,December[28]) -> 0 | AE14: =SUBTOTAL(103,December[29]) -> 0 | AF14: =SUBTOTAL(109,December[30]) -> 0 | AG14: =SUBTOTAL(109,December[31]) -> 0 | AH14: =SUBTOTAL(109,December[Total days]) -> 0 | AK14: =SUM(AL14:AP14) -> 5510000 | AL14: 4500000 | AM14: =$AI$5*August[[#This Row],[Total days]] -> 460000 | AN14: 50000 | AO14: 500000 | AP14: =$AC$5*June[[#This Row],[Working Day]] -> 0
AK15: =SUM(AK9:AK14) -> 28390000 | AL15: =SUM(AL9:AL14) -> 23500000 | AM15: =SUM(AM9:AM14) -> 2140000 | AN15: =SUM(AN9:AN14) -> 250000 | AO15: =SUM(AO9:AO14) -> 2500000 | AP15: =SUM(AP9:AP14) -> 0

Sheet Jan
D1: Employee absence schedule
D2: January
C4: Absence type key | D4: A | E4: Absent of work | H4: a | I4: Annual leave | L4: S | M4: Sick leave | X4: Amount Commission, LAK | AD4: Amount Commission/day | AJ4: Meal/day
U5: =4500000/AI9 -> 225000 | AD5: =X5/June[[#Totals],[Working Day]] -> 0 | AJ5: 20000
E6: Dates of absence | AJ6: =CalendarYear -> 2026
D7: =TEXT(WEEKDAY(DATE(CalendarYear,11,27),1),"aaa") -> Fri | E7: =TEXT(WEEKDAY(DATE(CalendarYear,11,28),1),"aaa") -> Sat | F7: =TEXT(WEEKDAY(DATE(CalendarYear,11,29),1),"aaa") -> Sun | G7: =TEXT(WEEKDAY(DATE(CalendarYear,11,30),1),"aaa") -> Mon | H7: =TEXT(WEEKDAY(DATE(CalendarYear,12,1),1),"aaa") -> Tue | I7: =TEXT(WEEKDAY(DATE(CalendarYear,12,2),1),"aaa") -> Wed | J7: =TEXT(WEEKDAY(DATE(CalendarYear,12,3),1),"aaa") -> Thu | K7: =TEXT(WEEKDAY(DATE(CalendarYear,12,4),1),"aaa") -> Fri | L7: =TEXT(WEEKDAY(DATE(CalendarYear,12,5),1),"aaa") -> Sat | M7: =TEXT(WEEKDAY(DATE(CalendarYear,12,6),1),"aaa") -> Sun | N7: =TEXT(WEEKDAY(DATE(CalendarYear,12,7),1),"aaa") -> Mon | O7: =TEXT(WEEKDAY(DATE(CalendarYear,12,8),1),"aaa") -> Tue | P7: =TEXT(WEEKDAY(DATE(CalendarYear,12,9),1),"aaa") -> Wed | Q7: =TEXT(WEEKDAY(DATE(CalendarYear,12,10),1),"aaa") -> Thu | R7: =TEXT(WEEKDAY(DATE(CalendarYear,12,11),1),"aaa") -> Fri | S7: =TEXT(WEEKDAY(DATE(CalendarYear,12,12),1),"aaa") -> Sat | T7: =TEXT(WEEKDAY(DATE(CalendarYear,12,13),1),"aaa") -> Sun | U7: =TEXT(WEEKDAY(DATE(CalendarYear,12,14),1),"aaa") -> Mon | V7: =TEXT(WEEKDAY(DATE(CalendarYear,12,15),1),"aaa") -> Tue | W7: =TEXT(WEEKDAY(DATE(CalendarYear,12,16),1),"aaa") -> Wed | X7: =TEXT(WEEKDAY(DATE(CalendarYear,12,17),1),"aaa") -> Thu | Y7: =TEXT(WEEKDAY(DATE(CalendarYear,12,18),1),"aaa") -> Fri | Z7: =TEXT(WEEKDAY(DATE(CalendarYear,12,19),1),"aaa") -> Sat | AA7: =TEXT(WEEKDAY(DATE(CalendarYear,12,20),1),"aaa") -> Sun | AB7: =TEXT(WEEKDAY(DATE(CalendarYear,12,21),1),"aaa") -> Mon | AC7: =TEXT(WEEKDAY(DATE(CalendarYear,12,22),1),"aaa") -> Tue | AD7: =TEXT(WEEKDAY(DATE(CalendarYear,12,23),1),"aaa") -> Wed | AE7: =TEXT(WEEKDAY(DATE(CalendarYear,12,24),1),"aaa") -> Thu | AF7: =TEXT(WEEKDAY(DATE(CalendarYear,12,25),1),"aaa") -> Fri | AG7: =TEXT(WEEKDAY(DATE(CalendarYear,12,19),1),"aaa") -> Sat | AH7: =TEXT(WEEKDAY(DATE(CalendarYear,12,20),1),"aaa") -> Sun
B8: No | C8: Employee name | D8: 26 | E8: 27 | F8: 28 | G8: 29 | H8: 30 | I8: 31 | J8: 1 | K8: 2 | L8: 3 | M8: 4 | N8: 5 | O8: 6 | P8: 7 | Q8: 8 | R8: 9 | S8: 10 | T8: 11 | U8: 12 | V8: 13 | W8: 14 | X8: 15 | Y8: 16 | Z8: 17 | AA8: 18 | AB8: 19 | AC8: 20 | AD8: 21 | AE8: 22 | AF8: 23 | AG8: 24 | AH8: 25 | AI8: Total days | AL8: Amount in month | AM8: Salary | AN8: Real working day | AO8: Meal | AP8: Phone | AQ8: OT | AR8: incentive | AS8: Commission
B9: 1 | C9: Mr. SOMPHONE XAYASA | D9: √ | G9: √ | H9: √ | I9: √ | K9: √ | N9: √ | O9: √ | P9: √ | Q9: √ | R9: √ | U9: √ | V9: √ | W9: √ | X9: √ | Y9: √ | AB9: √ | AC9: √ | AD9: √ | AE9: √ | AF9: √ | AI9: =COUNTA(November2[[#This Row],[26]:[25]]) -> 20 | AL9: =SUM(AM9:AU9) -> 10000000 | AM9: 10000000 | AT9: CEO
B10: 2 | K10: √ | AI10: =COUNTA(November2[[#This Row],[26]:[25]]) -> 1 | AL10: =SUM(AM10:AU10) -> 0 | AM10: 0 | AO10: =$AJ$5*October[[#This Row],[Total days]] -> 0 | AT10: CFO
B11: 2 | C11: MISS. SOUKSAKHONE CHONPATHOUMA | D11: √ | G11: √ | H11: √ | I11: √ | K11: √ | N11: √ | O11: √ | P11: √ | Q11: √ | R11: √ | U11: √ | V11: √ | W11: √ | X11: √ | Y11: √ | AB11: √ | AC11: √ | AD11: √ | AE11: √ | AF11: √ | AI11: =COUNTA(November2[[#This Row],[26]:[25]]) -> 20 | AL11: =SUM(AM11:AU11) -> 5000000 | AM11: 5000000 | AO11: =$AJ$5*October[[#This Row],[Total days]] -> 0 | AT11: CHR
B12: 3 | C12: Mss. CHAMPA LUANGAPHAI | D12: √ | G12: √ | H12: √ | I12: √ | K12: √ | N12: √ | O12: √ | P12: √ | Q12: √ | R12: √ | U12: √ | V12: √ | W12: √ | X12: √ | Y12: √ | AB12: √ | AC12: √ | AD12: √ | AE12: √ | AF12: √ | AI12: =COUNTA(November2[[#This Row],[26]:[25]]) -> 20 | AL12: 9000000 | AM12: 0 | AT12: MD | AV12: OT 26ວັນ | AW12: ເສົາ | AX12: ອາທິດ | AZ12: OT 22ວັນ | BA12: ເສົາ | BB12: ອາທິດ
B13: 4 | C13: Mr. KHAMLAR CHITTAMANY | D13: √ | G13: √ | H13: √ | I13: √ | K13: √ | N13: √ | O13: √ | P13: √ | Q13: √ | R13: √ | U13: √ | V13: √ | W13: √ | X13: √ | Y13: √ | AB13: √ | AC13: √ | AD13: √ | AE13: √ | AF13: √ | AI13: =COUNTA(November2[[#This Row],[26]:[25]]) -> 20 | AL13: =SUM(AM13:AU13) -> 2000000 | AM13: 2000000 | AT13: CONS | AV13: 5500000 | AW13: =(((AV13/26)/8)*150%)/100% -> 39663.462 | AX13: =(((AV13/26)/8)*250%)/100% -> 66105.769 | AZ13: 4250000 | BA13: =(((AZ13/22)/8)*150%)/100% -> 36221.591 | BB13: =(((AZ13/22)/8)*250%)/100% -> 60369.318
B14: 5 | C14: MS. OULAYVANH NGAVINAM | D14: √ | G14: √ | H14: √ | I14: √ | K14: √ | L14: 10 | N14: √ | O14: √ | P14: 3 | Q14: 6 | R14: √ | U14: √ | V14: √ | W14: √ | X14: 3 | Y14: √ | AB14: √ | AC14: √ | AD14: √ | AE14: √ | AF14: √ | AI14: =COUNTA(November2[[#This Row],[26]:[25]]) -> 21 | AL14: =SUM(AM14:AU14) -> 8906250 | AM14: 7500000 | AO14: =$AJ$5*October[[#This Row],[Total days]] -> 0 | AQ14: =AA39 -> 1406250 | AT14: ASS | AV14: 5125000 | AW14: =(((AV14/26)/8)*150%)/100% -> 36959.135 | AX14: =(((AV14/26)/8)*250%)/100% -> 61598.558 | AZ14: 4500000 | BA14: =(((AZ14/22)/8)*150%)/100% -> 38352.273 | BB14: =(((AZ14/22)/8)*250%)/100% -> 63920.455
B15: 6 | C15: MS. VILAYPHONE VONGPHACKDE | D15: √ | G15: √ | H15: √ | I15: √ | K15: √ | N15: √ | O15: √ | P15: 3 | Q15: √ | U15: √ | V15: √ | W15: √ | X15: 3 | AB15: √ | AC15: √ | AD15: √ | AE15: √ | AF15: √ | AI15: =COUNTA(November2[[#This Row],[26]:[25]]) -> 18 | AL15: =SUM(AM15:AU15) -> 5140113.6 | AM15: 4500000 | AO15: =AJ5*November2[[#This Row],[Total days]] -> 360000 | AP15: 50000 | AQ15: =AA41 -> 230113.64 | AT15: ACC | AV15: 4250000 | AW15: =(((AV15/26)/8)*150%)/100% -> 30649.038 | AX15: =(((AV15/26)/8)*250%)/100% -> 51081.731 | AZ15: 7500000 | BA15: =(((AZ15/22)/8)*150%)/100% -> 63920.455 | BB15: =(((AZ15/22)/8)*250%)/100% -> 106534.09
B16: 7 | C16: Mr. SIVONE MANACHACK (Vone) | D16: √ | E16: √ | G16: √ | H16: √ | I16: √ | K16: √ | L16: √ | N16: √ | O16: √ | Q16: √ | R16: √ | S16: √ | U16: √ | V16: √ | W16: √ | X16: √ | Y16: √ | Z16: √ | AA16: 8 | AB16: √ | AC16: √ | AD16: √ | AE16: √ | AF16: √ | AG16: √ | AI16: =COUNTA(November2[[#This Row],[26]:[25]]) -> 25 | AL16: =SUM(AM16:AU16) -> 6167788.5 | AM16: 5125000 | AO16: =AJ5*November2[[#This Row],[Total days]] -> 500000 | AP16: 50000 | AQ16: =AA34 -> 492788.46 | AT16: TECH | AV16: 5220000 | AW16: =(((AV16/26)/8)*150%)/100% -> 37644.231 | AX16: =(((AV16/26)/8)*250%)/100% -> 62740.385
B17: 8 | C17: Mr. SOMPHONE KEOPHILAVANH (Olay) | D17: √ | E17: √ | G17: √ | H17: √ | I17: √ | K17: √ | L17: √ | N17: √ | O17: √ | P17: √ | Q17: √ | R17: √ | S17: √ | U17: √ | V17: √ | W17: √ | X17: √ | Y17: √ | Z17: √ | AA17: 8 | AB17: √ | AC17: √ | AD17: √ | AE17: √ | AF17: √ | AG17: √ | AH17: 4 | AI17: =COUNTA(November2[[#This Row],[26]:[25]]) -> 27 | AL17: =SUM(AM17:AU17) -> 5442980.8 | AM17: 4250000 | AO17: =AJ5*November2[[#This Row],[Total days]] -> 540000 | AP17: 40000 | AQ17: =AA35 -> 612980.77 | AT17: TECH | AV17: 4000000 | AW17: =(((AV17/26)/8)*150%)/100% -> 28846.154 | AX17: =(((AV17/26)/8)*250%)/100% -> 48076.923
B18: 9 | C18: Mr. SONEPHET VIPHOMMA | Q18: √ | R18: √ | S18: √ | U18: √ | V18: √ | W18: √ | X18: √ | Y18: √ | Z18: √ | AB18: √ | AC18: √ | AD18: √ | AE18: √ | AF18: √ | AG18: √ | AH18: 4 | AI18: =COUNTA(November2[[#This Row],[26]:[25]]) -> 16 | AL18: =((AM18/26)*November2[[#This Row],[Total days]])+AO18+AP18 -> 3572307.7 | AM18: 5220000 | AO18: =AJ5*November2[[#This Row],[Total days]] -> 320000 | AP18: 40000 | AQ18: =AA37 -> 250961.54 | AT18: TECH
B19: 10 | C19: Mr. SATHEUAN MEUANGPHAUNE (NOK) | K19: √ | L19: √ | N19: √ | O19: √ | P19: √ | Q19: √ | R19: √ | S19: √ | U19: √ | V19: √ | W19: √ | Y19: √ | Z19: √ | AA19: 8 | AB19: √ | AC19: √ | AD19: √ | AE19: √ | AF19: √ | AG19: √ | AH19: 4 | AI19: =COUNTA(November2[[#This Row],[26]:[25]]) -> 21 | AL19: =((AM19/26)*November2[[#This Row],[Total days]])+AO19+AP19+AQ19+AR19+AS19 -> 4505673.1 | AM19: 4250000 | AO19: =AJ5*November2[[#This Row],[Total days]] -> 420000 | AP19: 40000 | AQ19: =AA36 -> 612980.77 | AT19: TECH
B20: 11 | C20: Mr. LOIY | U20: √ | V20: √ | W20: √ | X20: √ | Y20: √ | Z20: √ | AA20: 8 | AB20: √ | AC20: √ | AD20: √ | AE20: √ | AF20: √ | AI20: =COUNTA(November2[[#This Row],[26]:[25]]) -> 12 | AL20: =(AM20/26)*November2[[#This Row],[Total days]]+AQ20+AR20+AS20 -> 2348076.9 | AM20: 4000000 | AQ20: =AA38 -> 501923.08 | AT20: TECH
B21: 12 | C21: Mr. THAVONE CHANTHY (Add) | D21: √ | G21: √ | H21: √ | I21: √ | K21: √ | N21: √ | O21: √ | P21: √ | Q21: √ | R21: √ | U21: √ | V21: √ | W21: √ | X21: √ | Y21: √ | AB21: √ | AC21: √ | AD21: √ | AE21: √ | AF21: √ | AI21: =COUNTA(November2[[#This Row],[26]:[25]]) -> 20 | AL21: =SUM(AM21:AU21) -> 4940000 | AM21: 4500000 | AO21: =AJ5*November2[[#This Row],[Total days]] -> 400000 | AP21: 40000 | AT21: DRIVER
C22: MR. PHONEPASERT MALAVONG (Dido) | D22: √ | G22: √ | H22: √ | I22: √ | K22: √ | N22: √ | O22: √ | P22: √ | Q22: √ | R22: √ | U22: √ | V22: √ | W22: √ | X22: √ | Y22: √ | AB22: √ | AC22: √ | AD22: √ | AE22: √ | AF22: √ | AI22: =COUNTA(November2[[#This Row],[26]:[25]]) -> 20 | AL22: =AM22+AO22+AP22+AQ22+AR22+AS22 -> 4940000 | AM22: 4500000 | AO22: =AJ5*November2[[#This Row],[Total days]] -> 400000 | AP22: 40000 | AT22: DRIVER
B23: 13 | C23: Mr.KHANKHAM MARAVONG (Kol) | D23: √ | G23: √ | H23: √ | I23: √ | K23: √ | N23: √ | O23: √ | P23: √ | Q23: √ | R23: √ | U23: √ | V23: √ | W23: √ | X23: √ | Y23: √ | AB23: √ | AC23: √ | AD23: √ | AE23: √ | AF23: √ | AI23: =COUNTA(November2[[#This Row],[26]:[25]]) -> 20 | AL23: =SUM(AM23:AU23) -> 4940000 | AM23: 4500000 | AO23: =AJ5*November2[[#This Row],[Total days]] -> 400000 | AP23: 40000 | AT23: DRIVER
B24: 14 | C24: Mr. SUKAN MUENXAYYAPHOM (Yao) | D24: √ | G24: √ | H24: √ | I24: √ | K24: √ | L24: 10 | N24: √ | O24: 3 | P24: √ | Q24: 6 | R24: √ | U24: √ | V24: √ | W24: √ | X24: √ | Y24: √ | AB24: √ | AC24: √ | AD24: √ | AE24: √ | AF24: √ | AI24: =COUNTA(November2[[#This Row],[26]:[25]]) -> 21 | AL24: =SUM(AM24:AU24) -> 5688693.2 | AM24: 4500000 | AO24: =AJ5*November2[[#This Row],[Total days]] -> 420000 | AP24: 40000 | AQ24: =AA40 -> 728693.18 | AT24: PRO + WH
B25: 15 | C25: Mr. KITTIPHONG SEESOULASACK (beer) | D25: √ | G25: √ | H25: √ | I25: √ | K25: √ | N25: √ | O25: √ | P25: √ | Q25: √ | R25: √ | U25: √ | V25: √ | W25: √ | X25: √ | AB25: √ | AC25: √ | AD25: √ | AE25: √ | AF25: √ | AI25: =COUNTA(November2[[#This Row],[26]:[25]]) -> 19 | AL25: =SUM(AM25:AU25) -> 4670000 | AM25: 4250000 | AO25: =AJ5*November2[[#This Row],[Total days]] -> 380000 | AP25: 40000 | AT25: Merchandiser
B26: 16 | C26: Mr. PHOUTTHASONE SILIPANYA (Too) | D26: √ | G26: √ | H26: √ | I26: √ | K26: √ | N26: √ | O26: √ | P26: √ | Q26: √ | R26: √ | U26: √ | V26: √ | W26: √ | X26: √ | Y26: √ | AB26: √ | AC26: √ | AD26: √ | AE26: √ | AF26: √ | AI26: =COUNTA(November2[[#This Row],[26]:[25]]) -> 20 | AL26: =SUM(AM26:AU26) -> 4690000 | AM26: 4250000 | AO26: =AJ5*November2[[#This Row],[Total days]] -> 400000 | AP26: 40000 | AT26: Merchandiser
B27: 17 | C27: Mr. SOUKSAVANH PHANNIVONGSOR (Thop) | D27: √ | G27: √ | H27: √ | I27: √ | K27: √ | N27: √ | O27: √ | P27: √ | Q27: √ | R27: √ | U27: √ | V27: √ | W27: √ | X27: √ | Y27: √ | AB27: √ | AC27: √ | AD27: √ | AE27: √ | AF27: √ | AI27: =COUNTA(November2[[#This Row],[26]:[25]]) -> 20 | AL27: =SUM(AM27:AU27) -> 4690000 | AM27: 4250000 | AO27: =AJ5*November2[[#This Row],[Total days]] -> 400000 | AP27: 40000 | AT27: Merchandiser
B28: 19 | C28: MRS. DET THESAVONG | D28: √ | G28: √ | H28: √ | I28: √ | K28: √ | N28: √ | O28: √ | P28: √ | Q28: √ | R28: √ | U28: √ | V28: √ | W28: √ | X28: √ | Y28: √ | AB28: √ | AC28: √ | AD28: √ | AE28: √ | AF28: √ | AI28: =COUNTA(November2[[#This Row],[26]:[25]]) -> 20 | AL28: =AM28 -> 1500000 | AM28: 1500000 | AT28: HK
C29: =MonthName&" Total" -> Total | D29: =SUBTOTAL(103,November2[26]) -> 16 | E29: =SUBTOTAL(103,November2[27]) -> 2 | F29: =SUBTOTAL(103,November2[28]) -> 0 | G29: =SUBTOTAL(103,November2[29]) -> 16 | H29: =SUBTOTAL(103,November2[30]) -> 16 | I29: =SUBTOTAL(103,November2[31]) -> 16 | J29: =SUBTOTAL(103,November2[1]) -> 0 | K29: =SUBTOTAL(103,November2[2]) -> 17 | L29: =SUBTOTAL(103,November2[3]) -> 5 | M29: =SUBTOTAL(103,November2[4]) -> 0 | N29: =SUBTOTAL(103,November2[5]) -> 17 | O29: =SUBTOTAL(103,November2[6]) -> 17 | P29: =SUBTOTAL(103,November2[7]) -> 16 | Q29: =SUBTOTAL(103,November2[8]) -> 18 | R29: =SUBTOTAL(103,November2[9]) -> 17 | S29: =SUBTOTAL(103,November2[10]) -> 4 | T29: =SUBTOTAL(103,November2[11]) -> 0 | U29: =SUBTOTAL(103,November2[12]) -> 19 | V29: =SUBTOTAL(103,November2[13]) -> 19 | W29: =SUBTOTAL(103,November2[14]) -> 19 | X29: =SUBTOTAL(103,November2[15]) -> 18 | Y29: =SUBTOTAL(103,November2[16]) -> 17 | Z29: =SUBTOTAL(103,November2[17]) -> 5 | AA29: =SUBTOTAL(103,November2[18]) -> 4 | AB29: =SUBTOTAL(103,November2[19]) -> 19 | AC29: =SUBTOTAL(103,November2[20]) -> 19 | AD29: =SUBTOTAL(103,November2[21]) -> 19 | AE29: =SUBTOTAL(103,November2[22]) -> 19 | AF29: =SUBTOTAL(103,November2[23]) -> 19 | AG29: =SUBTOTAL(109,November2[24]) -> 0 | AH29: =SUBTOTAL(109,November2[25]) -> 12 | AI29: =SUBTOTAL(109,November2[Total days]) -> 380 | AL29: =SUM(AL9:AL28) -> 98141884 | AM29: =SUM(AM9:AM28) -> 84095000 | AO29: =SUM(AO9:AO28) -> 4940000 | AP29: =SUM(AP9:AP28) -> 500000 | AQ29: =SUM(AQ9:AQ28) -> 4836691.4 | AR29: =SUM(AR9:AR28) -> 0 | AS29: =SUM(AS9:AS28) -> 0
AB31: ລາຍເຊັນຜູ້ສະຫຼຸບ
C32: List name of OT | D32: Normal OT day | O32: OT holiday (Sunday) | AA32: Total | AG32: Notation | AQ32: ລາຍເຊັນຜູ້ສະຫຼຸບ
B33: 1 | C33: Mr. SOMPHONE XAYASA | I33: =#REF!*D33 -> #REF! | AA33: =I33+U33 -> #REF!
B34: 1 | C34: Mr. SIVONE MANACHACK (Vone) | I34: =AW14*D34 -> 0 | O34: 8 | U34: =AX14*O34 -> 492788.46 | AA34: =I34+U34 -> 492788.46
B35: 2 | C35: Mr. SOMPHONE KEOPHILAVANH (Olay) | I35: =AW15*D35 -> 0 | O35: 12 | U35: =AX15*O35 -> 612980.77 | AA35: =I35+U35 -> 612980.77
B36: 3 | C36: Mr. NOK | I36: =AW15*D36 -> 0 | O36: 12 | U36: =AX15*O36 -> 612980.77 | AA36: =I36+U36 -> 612980.77
B37: 4 | C37: Mr. SONEPHET VIPHOMMA | I37: =AW16*D37 -> 0 | O37: 4 | U37: =AX16*O37 -> 250961.54 | AA37: =I37+U37 -> 250961.54
B38: 5 | C38: Mr. LOIY | I38: =AW17*D38 -> 0 | O38: 8 | U38: =AX16*O38 -> 501923.08 | AA38: =I38+U38 -> 501923.08
B39: 6 | C39: MS. OULAYVANH NGAVINAM | D39: 22 | I39: =BA15*D39 -> 1406250 | U39: =BB15*O39 -> 0 | AA39: =I39+U39 -> 1406250
B40: 7 | C40: Mr. SUKAN MUENXAYYAPHOM (Yao) | D40: 19 | I40: =BA14*D40 -> 728693.18 | U40: =BB14*O40 -> 0 | AA40: =I40+U40 -> 728693.18
B41: 8 | C41: MS. VILAYPHONE VONGPHACKDE | D41: 6 | I41: =BA14*D41 -> 230113.64 | U41: =BB14*O41 -> 0 | AA41: =I41+U41 -> 230113.64
AA42: =SUM(AA34:AF41) -> 4836691.4
Y44: ລາຍເຊັນຜູ້ສະຫຼຸບ

Sheet Employee names
C2: Employee names | H2: =I4/J4 -> #DIV/0! | I2: Commission in May
I3: Payment | J3: Total day | K3: Commission
B4: NO | C4: Employee Names | D4: Column1 | E4: Salary | F4: Meal | G4: Phone | H4: OT | J4: =SUM(J5:J23) -> 0 | K4: =SUM(K5:K23) -> 0 | M4: Account Name | P4: Day start work
B5: 1 | C5: Mr. SOMPHONE XAYASA | D5: =SUM(E5:K5) -> 10000000 | E5: 10000000 | L5: CEO | M5: 010120000323774 001 | N5: SOMPHONE XAYASA MR | O5: BCEL | P5: N/A
B6: 2 | C6: Mss. CHAMPA LUANGAPHAI | D6: =SUM(E6:K6) -> 9000000 | E6: 9000000 | L6: CFO | M6: 018 1206740315 | N6: CHAMPA LUANGAPHAI MRS | O6: BCEL | P6: 46017
B7: 3 | C7: MISS. SOUKSAKHONE CHONPATHOUMA | D7: =SUM(E7:K7) -> 5000000 | E7: 5000000 | L7: CHR | M7: 010120000147973 001 | N7: SOUKSAKHONE CHONPATHOUMA MS | O7: BCEL | P7: N/A
B8: 4 | C8: Mr. KHAMLAR CHITTAMANY | D8: =SUM(E8:K8) -> 2000000 | E8: 2000000 | L8: CONS | M8: 160120000031308 001 | N8: KHAMLAR CHITTAMANY MR | O8: BCEL | P8: N/A
B9: 5 | C9: MS. OULAYVANH NGAVINAM | D9: =SUM(E9:K9) -> 7500000 | E9: 7500000 | L9: ASS | M9: 2201232467120 | N9: OULAIVANH NGAVINAM MS | O9: BCEL | P9: 45926
B10: 6 | C10: MS. VILAYPHONE VONGPHACKDE | D10: =SUM(E10:K10) -> 4990000 | E10: 4500000 | F10: 440000 | G10: 50000 | L10: ACC | M10: 098120002000662 001 | N10: VILAYPHONE VONGPHUKDEE MS | O10: BCEL | P10: 45962
B11: 7 | C11: Mr. SIVONE MANACHACK (Vone) | D11: =SUM(E11:K11) -> 5615000 | E11: 5125000 | F11: 440000 | G11: 50000 | L11: TECH | M11: 010120001634623 001 | N11: SIVONE MANACHACK MR | O11: BCEL | P11: N/A
B12: 8 | C12: Mr. SOMPHONE KEOPHILAVANH (Olay) | D12: =SUM(E12:K12) -> 4730000 | E12: 4250000 | F12: 440000 | G12: 40000 | L12: TECH | M12: 2221241489 533 | N12: SOMPHONE KEOPHILAVANH MR | O12: BCEL | P12: 45971
B13: 9 | C13: Mr. SONEPHET VIPHOMMA | D13: =SUM(E13:K13) -> 5700000 | E13: 5220000 | F13: 440000 | G13: 40000 | L13: TECH | M13: 221 12 09696743 | N13: SONEPHET VIPHOMMA MR | O13: BCEL | P13: 46030
B14: 10 | C14: Mr. SATHEUAN MEUANGPHAUNE (NOK) | D14: =SUM(E14:K14) -> 4730000 | E14: 4250000 | F14: 440000 | G14: 40000 | L14: TECH | M14: 010 12 0000531056 001 | N14: SATHEUAN MEUANGPHAUNE MR | O14: BCEL | P14: 46025
B15: 11 | C15: Mr. LOIY | D15: =SUM(E15:K15) -> 4000000 | E15: 4000000 | L15: TECH | M15: Cash | P15: 46034
B16: 12 | C16: MR. PHONEPASERT MALAVONG (Dido) | D16: =SUM(E16:K16) -> 4980000 | E16: 4500000 | F16: 440000 | G16: 40000 | L16: DRIVER | M16: 222 12 19862872 | N16: PHONEPASERT MALAVONG MR | O16: BCEL | P16: 46017
B17: 13 | C17: Mr. THAVONE CHANTHY (Add) | D17: =SUM(E17:K17) -> 4980000 | E17: 4500000 | F17: 440000 | G17: 40000 | L17: DRIVER | M17: 2221241426 220 | N17: THAVONE CHANTHY MR | O17: BCEL | P17: 45971
B18: 14 | C18: Mr.KHANKHAM MARAVONG (Kol) | D18: =SUM(E18:K18) -> 4980000 | E18: 4500000 | F18: 440000 | G18: 40000 | L18: DRIVER | M18: 010120000300443 001 | N18: KHANKHAM MALAVONG MR | O18: BCEL | P18: 45971
B19: 15 | C19: Mr. SUKAN MUENXAYYAPHOM (Yao) | D19: =SUM(E19:K19) -> 4980000 | E19: 4500000 | F19: 440000 | G19: 40000 | L19: Pro + WH | M19: 112120000447687 001 | N19: SUKAN MUENXAYYAPHOM MR | O19: BCEL | P19: 45972
B20: 16 | C20: Mr. KITTIPHONG SEESOULASACK (beer) | D20: =SUM(E20:K20) -> 4730000 | E20: 4250000 | F20: 440000 | G20: 40000 | L20: Merchandiser | M20: Cash | P20: 45971
B21: 17 | C21: Mr. PHOUTTHASONE SILIPANYA (Too) | D21: =SUM(E21:K21) -> 4730000 | E21: 4250000 | F21: 440000 | G21: 40000 | L21: Merchandiser | M21: 1501234315 049 | N21: PHOUTTHASONE SILIPANYA MR | O21: BCEL | P21: 45971
B22: 18 | C22: Mr. SOUKSAVANH PHANNIVONGSOR (Thop) | D22: =SUM(E22:K22) -> 4730000 | E22: 4250000 | F22: 440000 | G22: 40000 | L22: Merchandiser | M22: 222120001754213 001 | N22: SOUKSAVANH PHANNIVONGSOR MR | O22: BCEL | P22: 45971
B23: 19 | C23: MRS. DET THESAVONG | D23: =SUM(E23:K23) -> 1500000 | E23: 1500000 | L23: HK | M23: 010120000270485 001 | N23: DET THESAVONG MRS | O23: BCEL | P23: 45994
B24: Sum | D24: =SUM(EmployeeName[Column1]) -> 98875000

Sheet Sheet1
C2: Employee names | H2: =I4/J4 -> #DIV/0! | I2: Commission in May
I3: Payment | J3: Total day | K3: Commission
B4: NO | C4: Employee Names | D4: Column1 | E4: Salary | F4: Meal | G4: Phone | H4: OT | J4: =SUM(J5:J23) -> 0 | K4: =SUM(K5:K23) -> 0 | M4: Account Name | P4: Day start work
B5: 1 | C5: Mr. SOMPHONE XAYASA | D5: =SUM(E5:K5) -> 10000000 | E5: 10000000 | L5: CEO | M5: 010120000323774 001 | N5: SOMPHONE XAYASA MR | O5: BCEL
B6: 2 | C6: Mss. CHAMPA LUANGAPHAI | D6: =SUM(E6:K6) -> 9000000 | E6: 9000000 | L6: CFO
B7: 3 | C7: MISS. SOUKSAKHONE CHONPATHOUMA | D7: =SUM(E7:K7) -> 5000000 | E7: 5000000 | L7: CHR | M7: 010120000147973 001 | N7: SOUKSAKHONE CHONPATHOUMA MS | O7: BCEL
B8: 4 | C8: Mr. KHAMLAR CHITTAMANY | D8: =SUM(E8:K8) -> 2000000 | E8: 2000000 | L8: CONS | M8: 160120000031308 001 | N8: KHAMLAR CHITTAMANY MR | O8: BCEL
B9: 5 | C9: MS. OULAYVANH NGAVINAM | D9: =SUM(E9:K9) -> 7500000 | E9: 7500000 | L9: ASS | M9: 2201232467120 | N9: OULAIVANH NGAVINAM MS | O9: BCEL | P9: 45926
B10: 6 | C10: MS. VILAYPHONE VONGPHACKDE | D10: =SUM(E10:K10) -> 4990000 | E10: 4500000 | F10: 440000 | G10: 50000 | L10: ACC | M10: 098120002000662 001 | N10: VILAYPHONE VONGPHUKDEE MS | O10: BCEL | P10: 45962
B11: 7 | C11: Mr. SIVONE MANACHACK (Vone) | D11: =SUM(E11:K11) -> 5615000 | E11: 5125000 | F11: 440000 | G11: 50000 | L11: TECH | M11: 010120001634623 001 | N11: SIVONE MANACHACK MR | O11: BCEL
B12: 8 | C12: Mr. SOMPHONE KEOPHILAVANH (Olay) | D12: =SUM(E12:K12) -> 4730000 | E12: 4250000 | F12: 440000 | G12: 40000 | L12: TECH | M12: 2221241489 533 | N12: SOMPHONE KEOPHILAVANH MR | O12: BCEL | P12: 45971
B13: 9 | C13: Mr. TUSACKDA XAYASA (Tu) | D13: =SUM(E13:K13) -> 5990000 | E13: 5500000 | F13: 440000 | G13: 50000 | L13: TECH | M13: Cash
B14: 10 | D14: =SUM(E14:K14) -> 0
B15: 11 | D15: =SUM(E15:K15) -> 0
B16: 12 | C16: Mr. THAVONE CHANTHY (Add) | D16: =SUM(E16:K16) -> 4980000 | E16: 4500000 | F16: 440000 | G16: 40000 | L16: DRIVER | M16: 2221241426 220 | N16: THAVONE CHANTHY MR | O16: BCEL | P16: 45971
B17: 13 | C17: Mr.KHANKHAM MARAVONG (Kol) | D17: =SUM(E17:K17) -> 4980000 | E17: 4500000 | F17: 440000 | G17: 40000 | L17: DRIVER | M17: 010120000300443 001 | N17: KHANKHAM MALAVONG MR | O17: BCEL | P17: 45971
B18: 14 | C18: Mr. SUKAN MUENXAYYAPHOM (Yao) | D18: =SUM(E18:K18) -> 4980000 | E18: 4500000 | F18: 440000 | G18: 40000 | L18: DRIVER | M18: 112120000447687 001 | N18: SUKAN MUENXAYYAPHOM MR | O18: BCEL | P18: 45972
B19: 15 | C19: Mr. KITTIPHONG SEESOULASACK (beer) | D19: =SUM(E19:K19) -> 4730000 | E19: 4250000 | F19: 440000 | G19: 40000 | L19: Merchandiser | M19: Cash | P19: 45971
B20: 16 | C20: Mr. PHOUTTHASONE SILIPANYA (Too) | D20: =SUM(E20:K20) -> 4730000 | E20: 4250000 | F20: 440000 | G20: 40000 | L20: Merchandiser | M20: 1501234315 049 | N20: PHOUTTHASONE SILIPANYA MR | O20: BCEL | P20: 45971
B21: 17 | C21: Mr. SOUKSAVANH PHANNIVONGSOR (Thop) | D21: =SUM(E21:K21) -> 4730000 | E21: 4250000 | F21: 440000 | G21: 40000 | L21: Merchandiser | M21: 222120001754213 001 | N21: SOUKSAVANH PHANNIVONGSOR MR | O21: BCEL | P21: 45971
B22: 18 | C22: MRS. DET THESAVONG | D22: =SUM(E22:K22) -> 1500000 | E22: 1500000 | L22: HK | M22: 010120000270485 001 | N22: DET THESAVONG MRS | O22: BCEL | P22: 45994
B23: 19 | C23: Mss. SIRIPHUN KHOUNHAVONG (Tor) | D23: =SUM(E23:K23) -> 4000000 | E23: 4000000 | L23: HK | M23: Cash | P23: 45962 | Q23: ອອກແລ້ວ
B24: Sum | D24: =SUM(EmployeeName6[Column1]) -> 89455000
